Workbook

Sheet Cashflow_Misa
B1: 2026 - BẢNG THEO DÕI DÒNG TIỀN
D2: % | E2: TỔNG | F2: Jan | H2: Feb | J2: March | L2: April | N2: May | P2: June | R2: July | T2: August | V2: September | X2: October | Z2: November | AB2: December | AD2: %
B3: ĐẦU KỲ | I3: =G66 -> 10000 | K3: =I66 -> 10000 | M3: =K66 -> 10000 | O3: =M66 -> 10000 | Q3: =O66 -> 10000 | S3: =Q66 -> 10000 | U3: =S66 -> 10000 | W3: =U66 -> 10000 | X3: =V66 -> #DIV/0! | Y3: =W66 -> 10000 | AA3: =Y66 -> 10000 | AC3: =AA66 -> 10000
B4: LÃI/LỖ | E4: =G4+I4+K4+M4+O4+Q4+S4+U4+W4+Y4+AA4+AC4 -> 0 | G4: =G5-G16 -> 0 | H4: =H5-H16 -> 0 | I4: =I5-I16 -> 0 | J4: =J5-J16 -> 0 | K4: =K5-K16 -> 0 | L4: =L5-L16 -> 0 | M4: =M5-M16 -> 0 | N4: =N5-N16 -> 0 | ... U4: =U5-U16 -> 0 | W4: =W5-W16 -> 0 | Y4: =Y5-Y16 -> 0 | AA4: =AA5-AA16 -> 0 | AC4: =AC5-AC16 -> 0
B5: THU | D5: =E4/E5 -> #DIV/0! | E5: =G5+I5+K5+M5+O5+Q5+S5+U5+W5+Y5+AA5+AC5 -> 0 | G5: =SUBTOTAL(9,G6:G15)-G13 -> 0 | I5: =SUBTOTAL(9,I6:I15)-I13 -> 0 | K5: =SUBTOTAL(9,K6:K15)-K13 -> 0 | M5: =SUBTOTAL(9,M6:M15)-M13 -> 0 | O5: =SUBTOTAL(9,O6:O15)-O13 -> 0 | Q5: =SUBTOTAL(9,Q6:Q15)-Q13 -> 0 | S5: =SUBTOTAL(9,S6:S15)-S13 -> 0 | U5: =SUBTOTAL(9,U6:U15)-U13 -> 0 | W5: =SUBTOTAL(9,W6:W15)-W13 -> 0 | Y5: =SUBTOTAL(9,Y6:Y15)-Y13 -> 0 | AA5: =SUBTOTAL(9,AA6:AA15)-AA13 -> 0 | AC5: =SUBTOTAL(9,AC6:AC15)-AC13 -> 0
B6: Thu dự án | D6: =E6+E14+E11 -> 0 | E6: =G6+I6+K6+M6+O6+Q6+S6+U6+W6+Y6+AA6+AC6 -> 0 | F6: 521 | G6: =SUBTOTAL(9,$G$7:$G$9) -> 0 | H6: =I6/$I$5 -> #DIV/0! | I6: =SUBTOTAL(9,I7:I9) -> 0 | J6: =K6/$K$5 -> #DIV/0! | K6: =SUBTOTAL(9,K7:K9) -> 0 | L6: =M6/$M$5 -> #DIV/0! | M6: =SUBTOTAL(9,M7:M9) -> 0 | N6: =O6/$O$5 -> #DIV/0! | O6: =SUBTOTAL(9,O7:O9) -> 0 | P6: =Q6/$Q$5 -> #DIV/0! | Q6: =SUBTOTAL(9,Q7:Q9) -> 0 | R6: =S6/$S$5 -> #DIV/0! | S6: =SUBTOTAL(9,S7:S9) -> 0 | T6: =U6/$U$5 -> #DIV/0! | U6: =SUBTOTAL(9,U7:U9) -> 0 | W6: =SUBTOTAL(9,W7:W9) -> 0 | X6: =SUBTOTAL(9,X7:X9) -> 0 | Y6: =SUBTOTAL(9,Y7:Y9) -> 0 | Z6: =SUBTOTAL(9,Z7:Z9) -> 0 | AA6: =SUBTOTAL(9,AA7:AA9) -> 0 | AB6: =SUBTOTAL(9,AB7:AB9) -> 0 | AC6: =SUBTOTAL(9,AC7:AC9) -> 0 | AD6: =E6/$E$5 -> #DIV/0!
A7: 131+515.1-635.1 | C7: --T&M | D7: =E5-D6 -> 0 | E7: =G7+I7+K7+M7+O7+Q7+S7+U7+W7+Y7+AA7+AC7 -> 0 | AD7: =E7/$E$5 -> #DIV/0!
C8: -- Fixed Price | E8: =G8+I8+K8+M8+O8+Q8+S8+U8+W8+Y8+AA8+AC8 -> 0 | AD8: =E8/$E$5 -> #DIV/0!
C9: --Doanh thu từ môi giới, giới thiệu | D9: =D7-D6 -> 0 | E9: =G9+I9+K9+M9+O9+Q9+S9+U9+W9+Y9+AA9+AC9 -> 0 | F9: 0 | AD9: =E9/$E$5 -> #DIV/0!
B10: Thu đầu tư tài chính, tiết kiệm | E10: =G10+I10+K10+M10+O10+Q10+S10+U10+W10+Y10+AA10+AC10 -> 0 | AD10: =E10/$E$5 -> #DIV/0!
B11: Thu đầu tư R&D | E11: =G11+I11+K11+M11+O11+Q11+S11+U11+W11+Y11+AA11+AC11 -> 0 | AD11: =E11/$E$5 -> #DIV/0!
A12: 515.2+711.2 | B12: Thu khác | C12: Thu hoàn lương, cp gửi xe chi hộ, hoàn mua hộ cho KH, hoàn tiền chi hộ cho ds đính kèm hoạt động NB | E12: =G12+I12+K12+M12+O12+Q12+S12+U12+W12+Y12+AA12+AC12 -> 0 | F12: 9350 | AD12: =E12/$E$5 -> #DIV/0!
A13: 711.1 | B13: Thu từ khấu trừ thuế CTV | C13: =E14+E15 -> 0 | E13: =G13+I13+K13+M13+O13+Q13+S13+U13+W13+Y13+AA13+AC13 -> 0 | F13: 0 | AD13: =E13/$E$5 -> #DIV/0!
A14: 515.1-635.1 | B14: Lãi/lỗ TG | C14: Lãi/lỗ TG thanh toán | E14: =G14+I14+K14+M14+O14+Q14+S14+U14+W14+Y14+AA14+AC14 -> 0 | F14: 0 | AD14: =E14/$E$5 -> #DIV/0!
A15: 515.4-635.2 | C15: Lãi/lỗ TG rút tiền | E15: =G15+I15+K15+M15+O15+Q15+S15+U15+W15+Y15+AA15+AC15 -> 0 | AD15: =E15/$E$5 -> #DIV/0!
B16: CHI | E16: =G16+I16+K16+M16+O16+Q16+S16+U16+W16+Y16+AA16+AC16 -> 0 | G16: =SUBTOTAL(9,G17:G65) -> 0 | H16: =SUBTOTAL(9,H17:H65) -> 0 | I16: =SUBTOTAL(9,I17:I65) -> 0 | J16: =SUBTOTAL(9,J17:J65) -> 0 | K16: =SUBTOTAL(9,K17:K65) -> 0 | L16: =SUBTOTAL(9,L17:L65) -> 0 | M16: =SUBTOTAL(9,M17:M65) -> 0 | N16: =SUBTOTAL(9,N17:N65) -> 0 | ... AC16: =SUBTOTAL(9,AC17:AC65) -> 0
B17: Lương dự án | D17: =E17/$E$5 -> #DIV/0! | E17: =G17+I17+K17+M17+O17+Q17+S17+U17+W17+Y17+AA17+AC17 -> 0 | F17: -50928 | G17: =SUBTOTAL(9,G18:G22) -> 0 | H17: =SUBTOTAL(9,H18:H22) -> 0 | I17: =SUBTOTAL(9,I18:I22) -> 0 | J17: =SUBTOTAL(9,J18:J22) -> 0 | K17: =SUBTOTAL(9,K18:K22) -> 0 | L17: =SUBTOTAL(9,L18:L22) -> 0 | M17: =SUBTOTAL(9,M18:M22) -> 0 | N17: =SUBTOTAL(9,N18:N22) -> 0 | ... U17: =SUBTOTAL(9,U18:U22) -> 0 | V17: =W17/$W$6 -> #DIV/0! | W17: =SUBTOTAL(9,W18:W22) -> 0 | X17: =SUBTOTAL(9,X18:X22) -> 0 | Y17: =SUBTOTAL(9,Y18:Y22) -> 0 | Z17: =AA17/$AA$6 -> #DIV/0! | AA17: =SUBTOTAL(9,AA18:AA22) -> 0 | AB17: =SUBTOTAL(9,AB18:AB22) -> 0 | AC17: =SUBTOTAL(9,AC18:AC22) -> 0 | AD17: =E17/$E$5 -> #DIV/0!
C18: Lương nhân viên nội bộ | D18: =E18/$E$5 -> #DIV/0! | E18: =G18+I18+K18+M18+O18+Q18+S18+U18+W18+Y18+AA18+AC18 -> 0 | AD18: =E18/$E$5 -> #DIV/0!
C19: Lương nhân viên thuê ngoài trực tiếp (freelancer) | D19: =E19/$E$5 -> #DIV/0! | E19: =G19+I19+K19+M19+O19+Q19+S19+U19+W19+Y19+AA19+AC19 -> 0 | AD19: =E19/$E$5 -> #DIV/0!
C20: Lương nhân viên thuê nhà cung cấp (vendor) | D20: =E20/$E$5 -> #DIV/0! | E20: =G20+I20+K20+M20+O20+Q20+S20+U20+W20+Y20+AA20+AC20 -> 0 | AD20: =E20/$E$5 -> #DIV/0!
C21: Chi phí đầu tư đào tạo nhân lực (cử đi đào tạo, học tiếng anh...) | D21: =E21/$E$5 -> #DIV/0! | E21: =G21+I21+K21+M21+O21+Q21+S21+U21+W21+Y21+AA21+AC21 -> 0 | F21: 0 | AD21: =E21/$E$5 -> #DIV/0!
C22: Chi phí công tác, công cụ, sự kiện dành cho team dự án | D22: =E22/$E$5 -> #DIV/0! | E22: =G22+I22+K22+M22+O22+Q22+S22+U22+W22+Y22+AA22+AC22 -> 0 | AD22: =E22/$E$5 -> #DIV/0!
B23: Quản lý văn phòng | D23: =E23/$E$5 -> #DIV/0! | E23: =G23+I23+K23+M23+O23+Q23+S23+U23+W23+Y23+AA23+AC23 -> 0 | F23: -591650 | G23: =SUBTOTAL(9,G24:G26) -> 0 | H23: =SUBTOTAL(9,H24:H26) -> 0 | I23: =SUBTOTAL(9,I24:I26) -> 0 | J23: =SUBTOTAL(9,J24:J26) -> 0 | K23: =SUBTOTAL(9,K24:K27) -> 0 | L23: =SUBTOTAL(9,L24:L26) -> 0 | M23: =SUBTOTAL(9,M24:M26) -> 0 | N23: =SUBTOTAL(9,N24:N26) -> 0 | O23: =SUBTOTAL(9,O24:O27) -> 0 | P23: =SUBTOTAL(9,P24:P27) -> 0 | Q23: =SUBTOTAL(9,Q24:Q27) -> 0 | R23: =SUBTOTAL(9,R24:R27) -> 0 | S23: =SUBTOTAL(9,S24:S27) -> 0 | T23: =SUBTOTAL(9,T24:T26) -> 0 | U23: =SUBTOTAL(9,U24:U26) -> 0 | V23: =W23/$W$6 -> #DIV/0! | W23: =SUBTOTAL(9,W24:W26) -> 0 | X23: =SUBTOTAL(9,X24:X26) -> 0 | Y23: =SUBTOTAL(9,Y24:Y26) -> 0 | Z23: =AA23/$AA$6 -> #DIV/0! | AA23: =SUBTOTAL(9,AA24:AA26) -> 0 | AB23: =SUBTOTAL(9,AB24:AB26) -> 0 | AC23: =SUBTOTAL(9,AC24:AC26) -> 0 | AD23: =E23/$E$5 -> #DIV/0!
A24: chia theo pbo | C24: Chi phí thuê nhà | D24: =E24/$E$5 -> #DIV/0! | E24: =G24+I24+K24+M24+O24+Q24+S24+U24+W24+Y24+AA24+AC24 -> 0 | AD24: =E24/$E$5 -> #DIV/0!
C25: Dịch vụ/Điện/Nước/Gửi xe... | D25: =E25/$E$5 -> #DIV/0! | E25: =G25+I25+K25+M25+O25+Q25+S25+U25+W25+Y25+AA25+AC25 -> 0 | AD25: =E25/$E$5 -> #DIV/0!
C26: Chi phí mua sắm, phục vụ văn phòng cơ bản | D26: =E26/$E$5 -> #DIV/0! | E26: =G26+I26+K26+M26+O26+Q26+S26+U26+W26+Y26+AA26+AC26 -> 0 | AD26: =E26/$E$5 -> #DIV/0!
C27: Chi phí đầu tư Singapore | D27: =E27/$E$5 -> #DIV/0! | E27: =G27+I27+K27+M27+O27+Q27+S27+U27+W27+Y27+AA27+AC27 -> 0 | AD27: =E27/$E$5 -> #DIV/0!
B28: Chi phí đảm bảo chất lượng | D28: =E28/$E$5 -> #DIV/0! | E28: =G28+I28+K28+M28+O28+Q28+S28+U28+W28+Y28+AA28+AC28 -> 0 | F28: -1548 | G28: =SUBTOTAL(9,G29:G30) -> 0 | H28: =SUBTOTAL(9,H29:H30) -> 0 | I28: =SUBTOTAL(9,I29:I30) -> 0 | J28: =SUBTOTAL(9,J29:J30) -> 0 | K28: =SUBTOTAL(9,K29:K30) -> 0 | L28: =SUBTOTAL(9,L29:L30) -> 0 | M28: =SUBTOTAL(9,M29:M30) -> 0 | N28: =SUBTOTAL(9,N29:N30) -> 0 | ... U28: =SUBTOTAL(9,U29:U30) -> 0 | V28: =W28/$W$6 -> #DIV/0! | W28: =SUBTOTAL(9,W29:W30) -> 0 | X28: =SUBTOTAL(9,X29:X30) -> 0 | Y28: =SUBTOTAL(9,Y29:Y30) -> 0 | Z28: =AA28/$AA$6 -> #DIV/0! | AA28: =SUBTOTAL(9,AA29:AA30) -> 0 | AB28: =SUBTOTAL(9,AB29:AB30) -> 0 | AC28: =SUBTOTAL(9,AC29:AC30) -> 0 | AD28: =E28/$E$5 -> #DIV/0!
C29: ISO | D29: =E29/$E$6 -> #DIV/0! | E29: =G29+I29+K29+M29+O29+Q29+S29+U29+W29+Y29+AA29+AC29 -> 0 | AD29: =E29/$E$5 -> #DIV/0!
C30: Chi phí quản lý | D30: =E30/$E$6 -> #DIV/0! | E30: =G30+I30+K30+M30+O30+Q30+S30+U30+W30+Y30+AA30+AC30 -> 0 | AD30: =E30/$E$5 -> #DIV/0!
B31: Hành chính/ Nhân Sự | D31: =E31/$E$5 -> #DIV/0! | E31: =G31+I31+K31+M31+O31+Q31+S31+U31+W31+Y31+AA31+AC31 -> 0 | G31: =SUBTOTAL(9,G32:G33) -> 0 | H31: =SUBTOTAL(9,H32:H33) -> 0 | I31: =SUBTOTAL(9,I32:I33) -> 0 | J31: =SUBTOTAL(9,J32:J33) -> 0 | K31: =SUBTOTAL(9,K32:K33) -> 0 | L31: =SUBTOTAL(9,L32:L33) -> 0 | M31: =SUBTOTAL(9,M32:M33) -> 0 | N31: =SUBTOTAL(9,N32:N33) -> 0 | ... U31: =SUBTOTAL(9,U32:U33) -> 0 | V31: =W31/$W$6 -> #DIV/0! | W31: =SUBTOTAL(9,W32:W33) -> 0 | X31: =SUBTOTAL(9,X32:X33) -> 0 | Y31: =SUBTOTAL(9,Y32:Y33) -> 0 | Z31: =AA31/$AA$6 -> #DIV/0! | AA31: =SUBTOTAL(9,AA32:AA33) -> 0 | AB31: =SUBTOTAL(9,AB32:AB33) -> 0 | AC31: =SUBTOTAL(9,AC32:AC33) -> 0 | AD31: =E31/$E$5 -> #DIV/0!
A32: 6421.2 | C32: Lương/Thưởng cho bộ phận HCNS | D32: =E32/$E$6 -> #DIV/0! | E32: =G32+I32+K32+M32+O32+Q32+S32+U32+W32+Y32+AA32+AC32 -> 0 | AD32: =E32/$E$5 -> #DIV/0!
C33: Các chi phí hoạt động nội bộ | D33: =E33/$E$6 -> #DIV/0! | E33: =G33+I33+K33+M33+O33+Q33+S33+U33+W33+Y33+AA33+AC33 -> 0 | AD33: =E33/$E$5 -> #DIV/0!
B34: Kế toán/Tài Chính | D34: =E34/$E$5-0.3% -> #DIV/0! | E34: =G34+I34+K34+M34+O34+Q34+S34+U34+W34+Y34+AA34+AC34 -> 0 | G34: =SUBTOTAL(9,G35:G36) -> 0 | H34: =SUBTOTAL(9,H35:H36) -> 0 | I34: =SUBTOTAL(9,I35:I36) -> 0 | J34: =SUBTOTAL(9,J35:J36) -> 0 | K34: =SUBTOTAL(9,K35:K36) -> 0 | L34: =SUBTOTAL(9,L35:L36) -> 0 | M34: =SUBTOTAL(9,M35:M36) -> 0 | N34: =SUBTOTAL(9,N35:N36) -> 0 | ... U34: =SUBTOTAL(9,U35:U36) -> 0 | V34: =W34/$W$6 -> #DIV/0! | W34: =SUBTOTAL(9,W35:W36) -> 0 | X34: =SUBTOTAL(9,X35:X36) -> 0 | Y34: =SUBTOTAL(9,Y35:Y36) -> 0 | Z34: =AA34/$AA$6 -> #DIV/0! | AA34: =SUBTOTAL(9,AA35:AA36) -> 0 | AB34: =SUBTOTAL(9,AB35:AB36) -> 0 | AC34: =SUBTOTAL(9,AC35:AC36) -> 0 | AD34: =E34/$E$5 -> #DIV/0!
A35: 6422.6 | C35: Lương bộ phận kế toán | D35: =E35/$E$5-0.3% -> #DIV/0! | E35: =G35+I35+K35+M35+O35+Q35+S35+U35+W35+Y35+AA35+AC35 -> 0 | AD35: =E35/$E$5 -> #DIV/0!
C36: Chi phí xử lý thuế, các vấn đề về kế toán (nếu có) | D36: =E36/$E$5 -> #DIV/0! | E36: =G36+I36+K36+M36+O36+Q36+S36+U36+W36+Y36+AA36+AC36 -> 0 | AD36: =E36/$E$5 -> #DIV/0!
B37: Sales | D37: =E37/$E$5 -> #DIV/0! | E37: =G37+I37+K37+M37+O37+Q37+S37+U37+W37+Y37+AA37+AC37 -> 0 | F37: -5558 | G37: =SUBTOTAL(9,G38:G43) -> 0 | H37: =SUBTOTAL(9,H38:H43) -> 0 | I37: =SUBTOTAL(9,I38:I43) -> 0 | J37: =SUBTOTAL(9,J38:J43) -> 0 | K37: =SUBTOTAL(9,K38:K43) -> 0 | L37: =SUBTOTAL(9,L38:L43) -> 0 | M37: =SUBTOTAL(9,M38:M43) -> 0 | N37: =SUBTOTAL(9,N38:N43) -> 0 | ... U37: =SUBTOTAL(9,U38:U43) -> 0 | V37: =W37/$W$6 -> #DIV/0! | W37: =SUBTOTAL(9,W38:W43) -> 0 | X37: =SUBTOTAL(9,X38:X43) -> 0 | Y37: =SUBTOTAL(9,Y38:Y43) -> 0 | Z37: =AA37/$AA$6 -> #DIV/0! | AA37: =SUBTOTAL(9,AA38:AA43) -> 0 | AB37: =SUBTOTAL(9,AB38:AB43) -> 0 | AC37: =SUBTOTAL(9,AC38:AC43) -> 0 | AD37: =E37/$E$5 -> #DIV/0!
A38: 6421.3 | C38: Lương NV Sales | D38: =E38/$E$5 -> #DIV/0! | E38: =G38+I38+K38+M38+O38+Q38+S38+U38+W38+Y38+AA38+AC38 -> 0 | AD38: =E38/$E$5 -> #DIV/0!
A39: 6421.4 | C39: Công cụ phục vụ Sales | D39: =E39/$E$5 -> #DIV/0! | E39: =G39+I39+K39+M39+O39+Q39+S39+U39+W39+Y39+AA39+AC39 -> 0 | AD39: =E39/$E$5 -> #DIV/0!
A40: 6421.5 | C40: Tiếp khách | D40: =E40/$E$5 -> #DIV/0! | E40: =G40+I40+K40+M40+O40+Q40+S40+U40+W40+Y40+AA40+AC40 -> 0 | AD40: =E40/$E$5 -> #DIV/0!
A41: 6421.6 | C41: Công tác (sales) | D41: =E41/$E$5 -> #DIV/0! | E41: =G41+I41+K41+M41+O41+Q41+S41+U41+W41+Y41+AA41+AC41 -> 0 | AD41: =E41/$E$5 -> #DIV/0!
A42: 6421.7 | C42: Hội phí tham gia các tổ chức hiệp hội | D42: =E42/$E$5 -> #DIV/0! | E42: =G42+I42+K42+M42+O42+Q42+S42+U42+W42+Y42+AA42+AC42 -> 0 | AD42: =E42/$E$5 -> #DIV/0!
A43: 154 | C43: Commission_Sales | D43: =E43/$E$5 -> #DIV/0! | E43: =G43+I43+K43+M43+O43+Q43+S43+U43+W43+Y43+AA43+AC43 -> 0 | AD43: =E43/$E$5 -> #DIV/0!
B44: Marketing | D44: =E44/$E$5 -> #DIV/0! | E44: =G44+I44+K44+M44+O44+Q44+S44+U44+W44+Y44+AA44+AC44 -> 0 | G44: =SUBTOTAL(9,G45:G48) -> 0 | H44: =SUBTOTAL(9,H45:H48) -> 0 | I44: =SUBTOTAL(9,I45:I48) -> 0 | J44: =SUBTOTAL(9,J45:J48) -> 0 | K44: =SUBTOTAL(9,K45:K48) -> 0 | L44: =SUBTOTAL(9,L45:L48) -> 0 | M44: =SUBTOTAL(9,M45:M48) -> 0 | N44: =SUBTOTAL(9,N45:N48) -> 0 | ... U44: =SUBTOTAL(9,U45:U48) -> 0 | V44: =W44/$W$6 -> #DIV/0! | W44: =SUBTOTAL(9,W45:W48) -> 0 | X44: =SUBTOTAL(9,X45:X48) -> 0 | Y44: =SUBTOTAL(9,Y45:Y48) -> 0 | Z44: =AA44/$AA$6 -> #DIV/0! | AA44: =SUBTOTAL(9,AA45:AA48) -> 0 | AB44: =SUBTOTAL(9,AB45:AB48) -> 0 | AC44: =SUBTOTAL(9,AC45:AC48) -> 0 | AD44: =E44/$E$5 -> #DIV/0!
A45: 6421-15 | C45: Lương NV Marketing | D45: =E45/$E$6 -> #DIV/0! | E45: =G45+I45+K45+M45+O45+Q45+S45+U45+W45+Y45+AA45+AC45 -> 0 | AD45: =E45/$E$5 -> #DIV/0!
A46: 6421.8 | C46: Công tác (team marketing) | D46: =E46/$E$6 -> #DIV/0! | E46: =G46+I46+K46+M46+O46+Q46+S46+U46+W46+Y46+AA46+AC46 -> 0 | AD46: =E46/$E$5 -> #DIV/0!
A47: 6421.9 | C47: Event marketing | D47: =E47/$E$6 -> #DIV/0! | E47: =G47+I47+K47+M47+O47+Q47+S47+U47+W47+Y47+AA47+AC47 -> 0 | AD47: =E47/$E$5 -> #DIV/0!
A48: 1651537 | C48: Các CP khác (hạ tầng, công cụ phục vụ...) (team marketing) | D48: =E48/$E$6 -> #DIV/0! | E48: =G48+I48+K48+M48+O48+Q48+S48+U48+W48+Y48+AA48+AC48 -> 0 | AD48: =E48/$E$5 -> #DIV/0!
B49: Hạ tầng IT | D49: =E49/$E$5 -> #DIV/0! | E49: =G49+I49+K49+M49+O49+Q49+S49+U49+W49+Y49+AA49+AC49 -> 0 | G49: =SUBTOTAL(9,G50:G52) -> 0 | H49: =SUBTOTAL(9,H50:H52) -> 0 | I49: =SUBTOTAL(9,I50:I52) -> 0 | J49: =SUBTOTAL(9,J50:J52) -> 0 | K49: =SUBTOTAL(9,K50:K52) -> 0 | L49: =SUBTOTAL(9,L50:L52) -> 0 | M49: =SUBTOTAL(9,M50:M52) -> 0 | N49: =SUBTOTAL(9,N50:N52) -> 0 | ... U49: =SUBTOTAL(9,U50:U52) -> 0 | V49: =W49/$W$6 -> #DIV/0! | W49: =SUBTOTAL(9,W50:W52) -> 0 | X49: =SUBTOTAL(9,X50:X52) -> 0 | Y49: =SUBTOTAL(9,Y50:Y52) -> 0 | Z49: =AA49/$AA$6 -> #DIV/0! | AA49: =SUBTOTAL(9,AA50:AA52) -> 0 | AB49: =SUBTOTAL(9,AB50:AB52) -> 0 | AC49: =SUBTOTAL(9,AC50:AC52) -> 0 | AD49: =E49/$E$5 -> #DIV/0!
A50: 1651902 | C50: Chi phí Google Workspace | D50: =E50/$E$5 -> #DIV/0! | E50: =G50+I50+K50+M50+O50+Q50+S50+U50+W50+Y50+AA50+AC50 -> 0 | AD50: =E50/$E$5 -> #DIV/0!
A51: 1651933 | C51: Chi phí thuê Cloud Server (Amazon, DO, Vultr…) | D51: =E51/$E$5 -> #DIV/0! | E51: =G51+I51+K51+M51+O51+Q51+S51+U51+W51+Y51+AA51+AC51 -> 0 | AD51: =E51/$E$5 -> #DIV/0!
A52: 1651568 | C52: Chi phí đầu tư mua sắm bổ sung máy móc | D52: =E52/$E$5 -> #DIV/0! | E52: =G52+I52+K52+M52+O52+Q52+S52+U52+W52+Y52+AA52+AC52 -> 0 | AD52: =E52/$E$5 -> #DIV/0!
B53: Thuế & Bảo hiểm | D53: =E53/$E$5-0.85% -> #DIV/0! | E53: =G53+I53+K53+M53+O53+Q53+S53+U53+W53+Y53+AA53+AC53 -> 0 | G53: =SUBTOTAL(9,G54:G56) -> 0 | H53: =SUBTOTAL(9,H54:H56) -> 0 | I53: =SUBTOTAL(9,I54:I56) -> 0 | J53: =SUBTOTAL(9,J54:J56) -> 0 | K53: =SUBTOTAL(9,K54:K56) -> 0 | L53: =SUBTOTAL(9,L54:L56) -> 0 | M53: =SUBTOTAL(9,M54:M56) -> 0 | N53: =SUBTOTAL(9,N54:N56) -> 0 | ... U53: =SUBTOTAL(9,U54:U56) -> 0 | V53: =W53/$W$6 -> #DIV/0! | W53: =SUBTOTAL(9,W54:W56) -> 0 | X53: =SUBTOTAL(9,X54:X56) -> 0 | Y53: =SUBTOTAL(9,Y54:Y56) -> 0 | Z53: =AA53/$AA$6 -> #DIV/0! | AA53: =SUBTOTAL(9,AA54:AA56) -> 0 | AB53: =SUBTOTAL(9,AB54:AB56) -> 0 | AC53: =SUBTOTAL(9,AC54:AC56) -> 0 | AD53: =E53/$E$5 -> #DIV/0!
A54: 3334, 3335, 3339 | C54: Thuế phải đóng | D54: =E54/$E$5-0.85% -> #DIV/0! | E54: =G54+I54+K54+M54+O54+Q54+S54+U54+W54+Y54+AA54+AC54 -> 0 | AD54: =E54/$E$5 -> #DIV/0!
A55: 3383 | C55: BHXH | D55: =E55/$E$5 -> #DIV/0! | E55: =G55+I55+K55+M55+O55+Q55+S55+U55+W55+Y55+AA55+AC55 -> 0 | AD55: =E55/$E$5 -> #DIV/0!
A56: 6422.8 | C56: BH Tự nguyện | E56: =G56+I56+K56+M56+O56+Q56+S56+U56+W56+Y56+AA56+AC56 -> 0 | AD56: =E56/$E$5 -> #DIV/0!
B57: Thưởng (Bonus) | D57: =E57/$E$5-0.15% -> #DIV/0! | E57: =G57+I57+K57+M57+O57+Q57+S57+U57+W57+Y57+AA57+AC57 -> 0 | G57: =SUBTOTAL(9,G58:G62) -> 0 | H57: =SUBTOTAL(9,H58:H62) -> 0 | I57: =SUBTOTAL(9,I58:I62) -> 0 | J57: =SUBTOTAL(9,J58:J62) -> 0 | K57: =SUBTOTAL(9,K58:K62) -> 0 | L57: =SUBTOTAL(9,L58:L62) -> 0 | M57: =SUBTOTAL(9,M58:M62) -> 0 | N57: =SUBTOTAL(9,N58:N62) -> 0 | ... U57: =SUBTOTAL(9,U58:U62) -> 0 | V57: =W57/$W$6 -> #DIV/0! | W57: =SUBTOTAL(9,W58:W62) -> 0 | X57: =SUBTOTAL(9,X58:X62) -> 0 | Y57: =SUBTOTAL(9,Y58:Y62) -> 0 | Z57: =AA57/$AA$6 -> #DIV/0! | AA57: =SUBTOTAL(9,AA58:AA62) -> 0 | AB57: =SUBTOTAL(9,AB58:AB62) -> 0 | AC57: =SUBTOTAL(9,AC58:AC62) -> 0 | AD57: =E57/$E$5 -> #DIV/0!
A58: 334.4 | B58: Thưởng bonus dự án | C58: Thưởng bonus dự án | D58: =E58/$E$5 -> #DIV/0! | E58: =G58+I58+K58+M58+O58+Q58+S58+U58+W58+Y58+AA58+AC58 -> 0 | AD58: =E58/$E$5 -> #DIV/0!
A59: 334.9 +6421-12 | B59: Thưởng bonus tuyển dụng | C59: Chi phí tuyển dụng (Bonus tuyển dụng, Thuê dịch vụ …) | D59: =E59/$E$5 -> #DIV/0! | E59: =G59+I59+K59+M59+O59+Q59+S59+U59+W59+Y59+AA59+AC59 -> 0 | AD59: =E59/$E$5 -> #DIV/0!
A60: 6421-13 | B60: Thưởng marketing | C60: Thưởng MKT | D60: =E60/$E$5 -> #DIV/0! | E60: =G60+I60+K60+M60+O60+Q60+S60+U60+W60+Y60+AA60+AC60 -> 0 | AD60: =E60/$E$5 -> #DIV/0!
A61: 6421-14+ 334-11 | B61: Thưởng kinh doanh (sales) | C61: Thưởng kinh doanh | D61: =E61/$E$5 -> #DIV/0! | E61: =G61+I61+K61+M61+O61+Q61+S61+U61+W61+Y61+AA61+AC61 -> 0 | AD61: =E61/$E$5 -> #DIV/0!
A62: 6422.9 + 334-12 | B62: Thưởng kế toán | C62: Thưởng kế toán | D62: =E62/$E$5 -> #DIV/0! | E62: =G62+I62+K62+M62+O62+Q62+S62+U62+W62+Y62+AA62+AC62 -> 0 | AD62: =E62/$E$5 -> #DIV/0!
A63: 811 | B63: Các khoản chi khác (cho vay, tín dụng,...) | C63: Các khoản chi khác (cho vay, tín dụng,...) | D63: =E63/$E$5 -> #DIV/0! | E63: =G63+I63+K63+M63+O63+Q63+S63+U63+W63+Y63+AA63+AC63 -> 0 | AD63: =E63/$E$6 -> #DIV/0!
A64: 128 | B64: Khoản đi vay | C64: Khoản đi vay | D64: =E64/$E$6 -> #DIV/0! | E64: =G64+I64+K64+M64+O64+Q64+S64+U64+W64+Y64+AA64+AC64 -> 0 | AD64: =E64/$E$6 -> #DIV/0!
A65: 6423-334.8 | B65: Chi chủ sở hữu | C65: Lương/Thưởng cho CSH | D65: =E65/$E$5 -> #DIV/0! | E65: =G65+I65+K65+M65+O65+Q65+S65+U65+W65+Y65+AA65+AC65 -> 0 | AD65: =E65/$E$6 -> #DIV/0!
B66: CUỒI KỲ | G66: =G3+G5-G16 -> 10000 | H66: =H3+H5-H16 -> 0 | I66: =I3+I5-I16 -> 10000 | J66: =J3-J5-J16 -> 0 | K66: =K3+K5-K16 -> 10000 | L66: =L3+L5-L16 -> 0 | M66: =M3+M5-M16 -> 10000 | N66: =N3+N5-N16 -> 0 | O66: =O3+O5-O16 -> 10000 | P66: =P3+P5-P16 -> 0 | Q66: =Q3+Q5-Q16 -> 10000 | R66: =R3+R5-R16 -> 0 | ... AC66: =AC3+AC5-AC16 -> 10000

Sheet Bản sao của Cashflow_Misa 1
B1: 2025 - BẢNG THEO DÕI DÒNG TIỀN
B3: Chú giải: | G3: Text | I3: Text | K3: : Số liệu đã update thực tế, đã xảy ra
I4: Text | K4: : Số liệu planned
D6: % | E6: TỔNG | F6: Jan | H6: Feb | J6: March | L6: April | N6: May | P6: June | R6: July | T6: August | V6: September | X6: October | Z6: November | AB6: December | AD6: % | AF6: FINANCIAL INDEX
B7: ĐẦU KỲ | I7: =G69 -> 0 | K7: =I69 -> 0 | M7: =K69 -> 0 | O7: =M69 -> 0 | Q7: =O69 -> 0 | S7: =Q69 -> 0 | U7: =S69 -> 0 | W7: =U69 -> 0 | X7: =V69 -> 0 | Y7: =W69 -> 0 | AA7: =Y69 -> 0 | AC7: =AA69 -> 0 | AF7: Avg. 2M Expense | AG7: =E20/2 -> 0
B8: LÃI/LỖ | E8: =G8+I8+K8+M8+O8+Q8+S8+U8+W8+Y8+AA8+AC8 -> 0 | G8: =G9-G20 -> 0 | H8: =H9-H20 -> 0 | I8: =I9-I20 -> 0 | J8: =J9-J20 -> 0 | K8: =K9-K20 -> 0 | L8: =L9-L20 -> 0 | M8: =M9-M20 -> 0 | N8: =N9-N20 -> 0 | ... U8: =U9-U20 -> 0 | W8: =W9-W20 -> 0 | Y8: =Y9-Y20 -> 0 | AA8: =AA9-AA20 -> 0 | AC8: =AC9-AC20 -> 0 | AF8: OVERDRAFT | AG8: =2096000000+1000000000+100000000 -> 3196000000
B9: THU | E9: =G9+I9+K9+M9+O9+Q9+S9+U9+W9+Y9+AA9+AC9 -> 0 | G9: =SUBTOTAL(9,G10:G19)-G17 -> 0 | I9: =SUBTOTAL(9,I10:I19)-I17 -> 0 | K9: =SUBTOTAL(9,K10:K19)-K17 -> 0 | M9: =SUBTOTAL(9,M10:M19)-M17 -> 0 | O9: =SUBTOTAL(9,O10:O19)-O17 -> 0 | Q9: =SUBTOTAL(9,Q10:Q19)-Q17 -> 0 | S9: =SUBTOTAL(9,S10:S19)-S17 -> 0 | U9: =SUBTOTAL(9,U10:U19)-U17 -> 0 | W9: =SUBTOTAL(9,W10:W19)-W17 -> 0 | Y9: =SUBTOTAL(9,Y10:Y19)-Y17 -> 0 | AA9: =SUBTOTAL(9,AA10:AA19)-AA17 -> 0 | AC9: =SUBTOTAL(9,AC10:AC19)-AC17 -> 0 | AF9: Loan | AG9: 200000000
B10: Thu dự án | AD10: =E10/$E$9 -> #DIV/0! | AF10: ET. Current Ratio | AG10: =(I69+AG8+AG9)/AG7 -> #DIV/0!
A11: 131+515.1-635.1 | C11: --T&M | AD11: =E11/$E$9 -> #DIV/0! | AF11: ROS in Jan | AG11: =AG15/AG13 -> #DIV/0!
C12: -- Fixed Price | AD12: =E12/$E$9 -> #DIV/0! | AF12: ROS in 2025 | AG12: =AG18/AG16 -> #DIV/0!
C13: --Doanh thu từ môi giới, giới thiệu | AD13: =E13/$E$9 -> #DIV/0! | AF13: Total Income Feb | AG13: =I9 -> 0
B14: Thu đầu tư tài chính, tiết kiệm | AD14: =E14/$E$9 -> #DIV/0! | AF14: Total Expense Feb | AG14: =I20 -> 0
B15: Thu đầu tư R&D | AD15: =E15/$E$9 -> #DIV/0! | AF15: Net Earning Feb | AG15: =AG13-AG14 -> 0
A16: 515.2+711.2 | B16: Thu khác | C16: Thu hoàn lương, cp gửi xe chi hộ, hoàn mua hộ cho KH, hoàn tiền chi hộ cho ds đính kèm hoạt động NB | AD16: =E16/$E$9 -> #DIV/0! | AF16: Total Income 2025 | AG16: =E9 -> 0
A17: 711.1 | B17: Thu từ khấu trừ thuế CTV | AD17: =E17/$E$9 -> #DIV/0! | AF17: Total Expense 2025 | AG17: =E20 -> 0
A18: 515.1-635.1 | B18: Lãi/lỗ TG | C18: Lãi/lỗ TG thanh toán | AD18: =E18/$E$9 -> #DIV/0! | AF18: Net Earning 2025 | AG18: =AG16-AG17 -> 0
A19: 515.4-635.2 | C19: Lãi/lỗ TG rút tiền | AD19: =E19/$E$9 -> #DIV/0!
B20: CHI
B21: Lương dự án | AD21: =E21/$E$9 -> #DIV/0!
B22: 334.1 | C22: Lương nhân viên nội bộ | AD22: =E22/$E$9 -> #DIV/0!
B23: 334.2 | C23: Lương nhân viên thuê ngoài trực tiếp (freelancer) | AD23: =E23/$E$9 -> #DIV/0!
B24: 331 | C24: Lương nhân viên thuê nhà cung cấp (vendor) | AD24: =E24/$E$9 -> #DIV/0!
B25: 6421-17 | C25: Chi phí đầu tư đào tạo nhân lực (cử đi đào tạo, học tiếng anh...) | AD25: =E25/$E$9 -> #DIV/0!
B26: 154 | C26: Chi phí công tác, công cụ, sự kiện dành cho team dự án | AD26: =E26/$E$9 -> #DIV/0!
B27: Quản lý văn phòng | AD27: =E27/$E$9 -> #DIV/0!
A28: chia theo pbo | B28: 242 | C28: Chi phí thuê nhà | AD28: =E28/$E$9 -> #DIV/0!
B29: 6422.2 | C29: Dịch vụ/Điện/Nước/Gửi xe... | AD29: =E29/$E$9 -> #DIV/0!
B30: 6422.3 | C30: Chi phí mua sắm, phục vụ văn phòng cơ bản | AD30: =E30/$E$9 -> #DIV/0!
B31: Chi phí đảm bảo chất lượng | AD31: =E31/$E$9 -> #DIV/0!
B32: 6421.1 | C32: ISO | AD32: =E32/$E$9 -> #DIV/0!
B33: 6422.4 | C33: Chi phí quản lý | AD33: =E33/$E$9 -> #DIV/0!
B34: Hành chính/ Nhân Sự | AD34: =E34/$E$9 -> #DIV/0!
A35: 6421.2 | B35: 334.5 | C35: Lương/Thưởng cho bộ phận HCNS | AD35: =E35/$E$9 -> #DIV/0!
B36: 6422.5 | C36: Các chi phí hoạt động nội bộ | AD36: =E36/$E$9 -> #DIV/0!
B37: Kế toán/Tài Chính | AD37: =E37/$E$9 -> #DIV/0!
A38: 6422.6 | B38: 334.3 | C38: Lương bộ phận kế toán | AD38: =E38/$E$9 -> #DIV/0!
B39: 6422.7 | C39: Chi phí xử lý thuế, các vấn đề về kế toán (nếu có) | AD39: =E39/$E$9 -> #DIV/0!
B40: Sales | AD40: =E40/$E$9 -> #DIV/0! | AE40: =8/100*E10 -> 0 | AF40: =AE40-E40-E47 -> 0
A41: 6421.3 | B41: 334.6 | C41: Lương NV Sales | AD41: =E41/$E$9 -> #DIV/0!
A42: 6421.4 | C42: Công cụ phục vụ Sales | AD42: =E42/$E$9 -> #DIV/0!
A43: 6421.5 | C43: Tiếp khách | AD43: =E43/$E$9 -> #DIV/0!
A44: 6421.6 | C44: Công tác (sales) | AD44: =E44/$E$9 -> #DIV/0!
A45: 6421.7 | C45: Hội phí tham gia các tổ chức hiệp hội | AD45: =E45/$E$9 -> #DIV/0!
A46: 154 | C46: Commission_Sales | AD46: =E46/$E$9 -> #DIV/0!
B47: Marketing | AD47: =E47/$E$9 -> #DIV/0!
A48: 6421-15 | B48: 334.7 | C48: Lương NV Marketing | AD48: =E48/$E$9 -> #DIV/0!
A49: 6421.8 | C49: Công tác (team marketing) | AD49: =E49/$E$9 -> #DIV/0!
A50: 6421.9 | C50: Event marketing | AD50: =E50/$E$9 -> #DIV/0!
A51: 1651537 | C51: Các CP khác (hạ tầng, công cụ phục vụ...) (team marketing) | AD51: =E51/$E$9 -> #DIV/0!
B52: Hạ tầng IT | AD52: =E52/$E$9 -> #DIV/0!
A53: 1651902 | B53: 1651902 | C53: Chi phí Google Workspace | AD53: =E53/$E$9 -> #DIV/0!
A54: 1651933 | B54: 1651933 | C54: Chi phí thuê Cloud Server (Amazon, DO, Vultr…) | AD54: =E54/$E$9 -> #DIV/0!
A55: 1651568 | C55: Chi phí đầu tư mua sắm bổ sung máy móc | AD55: =E55/$E$9 -> #DIV/0!
B56: Thuế & Bảo hiểm | AD56: =E56/$E$9 -> #DIV/0!
A57: 3334, 3335, 3339 | C57: Thuế phải đóng | AD57: =E57/$E$9 -> #DIV/0!
A58: 3383 | C58: BHXH | AD58: =E58/$E$9 -> #DIV/0!
A59: 6422.8 | C59: BH Tự nguyện | AD59: =E59/$E$9 -> #DIV/0!
B60: Thưởng (Bonus) | AD60: =E60/$E$9 -> #DIV/0!
A61: 334.4 | B61: Thưởng bonus dự án | C61: Thưởng bonus dự án | AD61: =E61/$E$9 -> #DIV/0!
A62: 334.9 +6421-12 | B62: Thưởng bonus tuyển dụng | C62: Chi phí tuyển dụng (Bonus tuyển dụng, Thuê dịch vụ …) | AD62: =E62/$E$9 -> #DIV/0!
A63: 6421-13 | B63: Thưởng marketing | C63: Thưởng MKT | AD63: =E63/$E$9 -> #DIV/0!
A64: 6421-14+ 334-11 | B64: Thưởng kinh doanh (sales) | C64: Thưởng kinh doanh | AD64: =E64/$E$9 -> #DIV/0!
A65: 6422.9 + 334-12 | B65: Thưởng kế toán | C65: Thưởng kế toán | AD65: =E65/$E$9 -> #DIV/0!
A66: 811 | B66: Các khoản chi khác (cho vay, tín dụng,...) | C66: Các khoản chi khác (cho vay, tín dụng,...) | AD66: =E66/$E$10 -> #DIV/0!
A67: 128 | B67: Khoản tiết kiệm | C67: Khoản tiết kiệm | AD67: =E67/$E$10 -> #DIV/0!
A68: 6423-334.8 | B68: Chi chủ sở hữu | C68: Lương/Thưởng cho CSH | AD68: =E68/$E$10 -> #DIV/0!
B69: CUỒI KỲ
I70: =I69+AG8+AG9 -> 3396000000 | K70: =AG8*100/I70 -> 94.110718
G71: Jan | I71: Feb | K71: Mar | M71: Apr | O71: May | Q71: Jun | S71: Jul | U71: Aug | W71: Sep | Y71: Oct | AA71: Nov | AC71: Dec
B72: Số dư TK | E72: =G72-G69 -> 5728561100 | G72: =SUM(G73:G76) -> 5728561100 | H72: =SUM(H73:H76) -> 0 | I72: =SUM(I73:I76) -> 5659715082 | J72: =SUM(J73:J76) -> 0 | K72: =SUM(K73:K76) -> 0 | L72: =SUM(L73:L76) -> 0 | M72: =SUM(M73:M76) -> 0 | N72: =SUM(N73:N76) -> 0 | ... AC72: =SUM(AC73:AC76) -> 0
B73: 16 | C73: TK Doanh thu | G73: 78615597 | I73: 5110
C74: TK tích lũy dự phòng | G74: =5647272263 -902459381 -708670598 +81288837 -665795 -78615597 -75807 -1552693 -377830 -> 4036143399 | I74: =5560790939 +99089143 -I73-I75-I76-165000 -> 4533361197
B75: 46 | C75: TK cho CSH | G75: 377830 | I75: 268857
B76: 28,21,53,Payoneer, vp | C76: TK chi phí | G76: =708670598+665795+902459381 +75807 +1552693 -> 1613424274 | I76: =460412894 +97186561 +75807 +567016963 +1552693 -165000 -> 1126079918
B77: TÀI KHOẢN NGÂN HÀNG (Ngày 1 hàng tháng) | G77: =SUM(G78:G84) -> 10473449789 | H77: =SUM(H78:H84) -> 0 | I77: =SUM(I78:I84) -> 10760168934 | J77: =SUM(J78:J84) -> 0 | K77: =SUM(K78:K84) -> 0 | L77: =SUM(L78:L84) -> 0 | M77: =SUM(M78:M84) -> 0 | N77: =SUM(N78:N84) -> 0 | ... AC77: =SUM(AC78:AC84) -> 0
B78: --Techcombank DN | G78: =81288837-1552693-75807 -> 79660337 | I78: =99089143 -1552693-75807 -> 97460643
B79: --Techcombank CN | G79: 902459381 | I79: =460412894-165000 -> 460247894
B80: --Quy USD-VND | G80: =1528473273 +708670598 +2014319228 +31182813 +75807 -> 4282721719 | I80: =1591271587 +567016963 +2410694905 +31182813 +75807 -> 4600242075
B81: --GBP | G81: 68580800 | I81: 68580800
B82: --VPBank DN | G82: 1552693 | I82: 1552693
B83: --EUR | G83: 393586170 | I83: 431630977
B84: Tiết kiệm | G84: =G80+G83+G81 -> 4744888689 | H84: =H80+H83+H81 -> 0 | I84: =I80+I83+I81 -> 5100453852
I86: =I83/I77 -> 0.040113773
I87: =I81/I77 -> 0.0063735802
I88: =I80/I77 -> 0.42752508

Sheet Bản sao của Cashflow_Misa
B1: 2024 - BẢNG THEO DÕI DÒNG TIỀN
B3: Chú giải: | G3: Text | I3: Text | K3: : Số liệu đã update thực tế, đã xảy ra
I4: Text | K4: : Số liệu planned
D6: % | E6: TỔNG | F6: Jan | H6: Feb | J6: March | L6: April | N6: May | P6: June | R6: July | T6: August | V6: September | X6: October | Z6: November | AB6: December | AD6: % | AF6: FINANCIAL INDEX
B7: ĐẦU KỲ | G7: 2686639687 | I7: =G68 -> 4239048626 | K7: =I68 -> 3522316950 | M7: =K68 -> 3772272859 | O7: =M68 -> 3911889608 | Q7: =O68 -> 3973634228 | S7: =Q68 -> 4822733262 | U7: =S68 -> 5058911628 | W7: =U68 -> 4785275712 | X7: =V68 -> 0 | Y7: =W68 -> 4952988949 | AA7: =Y68 -> 5256312713 | AC7: =AA68 -> 5463955565 | AF7: Avg. 11M Expense | AG7: =E19/11 -> 2.0502953e+09
B8: LÃI/LỖ | E8: =G8+I8+K8+M8+O8+Q8+S8+U8+W8+Y8+AA8+AC8 -> 1157095616 | G8: =G9-G19 -> 1552408939 | H8: =H9-H19 -> 0 | I8: =I9-I19 -> -716731676 | J8: =J9-J19 -> 0 | K8: =K9-K19 -> 249955909 | L8: =L9-L19 -> 0 | M8: =M9-M19 -> 139616749 | N8: =N9-N19 -> 0 | ... U8: =U9-U19 -> -273635916 | W8: =W9-W19 -> 167713237 | Y8: =Y9-Y19 -> 303323764 | AA8: =AA9-AA19 -> 207642852 | AC8: =AC9-AC19 -> -1620220262 | AF8: OVERDRAFT | AG8: =2096000000+1000000000+100000000 -> 3196000000
B9: THU | E9: =G9+I9+K9+M9+O9+Q9+S9+U9+W9+Y9+AA9+AC9 -> 23710343643 | G9: =SUBTOTAL(9,G10:G18)-G16 -> 3274924980 | I9: =SUBTOTAL(9,I10:I18)-I16 -> 1646972576 | K9: =SUBTOTAL(9,K10:K18)-K16 -> 1809790827 | M9: =SUBTOTAL(9,M10:M18)-M16 -> 1830212715 | O9: =SUBTOTAL(9,O10:O18)-O16 -> 1923384218 | Q9: =SUBTOTAL(9,Q10:Q18)-Q16 -> 2348702879 | S9: =SUBTOTAL(9,S10:S18)-S16 -> 1937537786 | U9: =SUBTOTAL(9,U10:U18)-U16 -> 1888078435 | W9: =SUBTOTAL(9,W10:W18)-W16 -> 1879611092 | Y9: =SUBTOTAL(9,Y10:Y18)-Y16 -> 2555920718 | AA9: =SUBTOTAL(9,AA10:AA18)-AA16 -> 2516690542 | AC9: =SUBTOTAL(9,AC10:AC18)-AC16 -> 98516875 | AF9: Loan | AG9: 200000000
B10: Thu dự án | E10: =G10+I10+K10+M10+O10+Q10+S10+U10+W10+Y10+AA10+AC10 -> 22415957275 | F10: =G10/$G$9 -> 0.68189884 | G10: =SUBTOTAL(9,$G$11:$G$13) -> 2233167559 | H10: =I10/$I$9 -> 0.98321479 | I10: =SUBTOTAL(9,I11:I13) -> 1619327800 | J10: =K10/$K$9 -> 0.97515353 | K10: =SUBTOTAL(9,K11:K13) -> 1764823908 | L10: =M10/$M$9 -> 0.98556087 | M10: =SUBTOTAL(9,M11:M13) -> 1803786037 | N10: =O10/$O$9 -> 0.97745496 | O10: =SUBTOTAL(9,O11:O13) -> 1880021436 | P10: =Q10/$Q$9 -> 0.99158313 | Q10: =SUBTOTAL(9,Q11:Q13) -> 2328934149 | R10: =S10/$S$9 -> 0.98113774 | S10: =SUBTOTAL(9,S11:S13) -> 1900991447 | T10: =U10/$U$9 -> 1.0239262 | U10: =SUBTOTAL(9,U11:U13) -> 1933252957 | W10: =SUBTOTAL(9,W11:W13) -> 1858161375 | X10: =SUBTOTAL(9,X11:X13) -> 1 | Y10: =SUBTOTAL(9,Y11:Y13) -> 2537335754 | Z10: =SUBTOTAL(9,Z11:Z13) -> 1 | AA10: =SUBTOTAL(9,AA11:AA13) -> 2462282592 | AB10: =SUBTOTAL(9,AB11:AB13) -> 0 | AC10: =SUBTOTAL(9,AC11:AC13) -> 93872261 | AD10: =E10/$E$9 -> 0.94540837 | AF10: ET. Current Ratio | AG10: =(Q68+AG8)/AG7 -> 3.9110139
A11: 131+515.1-635.1 | C11: --T&M | E11: =G11+I11+K11+M11+O11+Q11+S11+U11+W11+Y11+AA11+AC11 -> 19723937155 | F11: 0.9353 | G11: 2088667559 | H11: 1 | I11: 1619327800 | J11: 0.9188 | K11: 1621543108 | L11: 0.9077 | M11: 1661209237 | N11: 0.8508 | O11: 1636406123 | P11: 0.7989 | Q11: 1876345517 | R11: 0.8613 | S11: 1668879138 | T11: =U11/$U$9 -> 0.96547217 | U11: 1822887188 | V11: =W11/$W$10 -> 0.90535682 | W11: 1682299075 | X11: =Y11/$Y$10 -> 0.7480725 | Y11: =1943349196 -45238095 -> 1898111101 | Z11: =AA11/$AA$10 -> 0.8548097 | AA11: 2104783048 | AC11: 43478261 | AD11: =E11/$E$9 -> 0.83187057 | AF11: ROS in Nov | AG11: =AG15/AG13 -> 0.082506311
C12: -- Fixed Price | E12: =G12+I12+K12+M12+O12+Q12+S12+U12+W12+Y12+AA12+AC12 -> 2692020120 | F12: 0.0647 | G12: 144500000 | H12: 0 | I12: 0 | J12: 0.0812 | K12: 143280800 | L12: 0.0779 | M12: 142576800 | N12: 0.1267 | O12: 243615313 | P12: 0.1927 | Q12: 452588632 | R12: 0.1198 | S12: 232112309 | T12: =U12/$U$9 -> 0.058454017 | U12: 110365769 | V12: =W12/$W$10 -> 0.094643179 | W12: 175862300 | X12: =Y12/$Y$10 -> 0.2519275 | Y12: =639469253-244600 -> 639224653 | Z12: =AA12/$AA$10 -> 0.1451903 | AA12: 357499544 | AC12: 50394000 | AD12: =E12/$E$9 -> 0.11353779 | AF12: ROS in 2024 | AG12: =AG18/AG16 -> 0.048801301
C13: --Doanh thu từ môi giới, giới thiệu | E13: =G13+I13+K13+M13+O13+Q13+S13+U13+W13+Y13+AA13+AC13 -> 0 | F13: 0 | G13: 0 | H13: 0 | I13: 0 | J13: 0 | K13: 0 | L13: 0 | M13: 0 | N13: 0 | O13: 0 | P13: 0 | Q13: 0 | R13: 0 | S13: 0 | T13: =U13/$U$9 -> 0 | U13: 0 | V13: =W13/$W$10 -> 0 | X13: =Y13/$Y$10 -> 0 | Z13: =AA13/$AA$10 -> 0 | AD13: =E13/$E$9 -> 0 | AF13: Total Income Nov | AG13: =AA9 -> 2516690542
B14: Thu đầu tư tài chính, tiết kiệm | E14: =G14+I14+K14+M14+O14+Q14+S14+U14+W14+Y14+AA14+AC14 -> 1042679674 | F14: 0.4595 | G14: 1026096751 | H14: 0 | I14: 0 | J14: 0 | K14: 0 | L14: 0.0001 | M14: 138136 | N14: 0 | O14: 0 | P14: 0 | Q14: 0 | R14: 0 | S14: 0 | T14: =U14/$U$9 -> 0 | U14: 0 | V14: =W14/$W$10 -> 0 | X14: =Y14/$Y$10 -> 0 | Z14: =AA14/$AA$10 -> 0.0066786757 | AA14: 16444787 | AD14: =E14/$E$9 -> 0.04397573 | AF14: Total Expense Nov | AG14: =AA19 -> 2309047690
A15: 515.2+711.2 | B15: Thu khác | C15: Thu hoàn lương, cp gửi xe chi hộ, hoàn mua hộ cho KH, hoàn tiền chi hộ cho ds đính kèm hoạt động NB | E15: =G15+I15+K15+M15+O15+Q15+S15+U15+W15+Y15+AA15+AC15 -> 203096291 | F15: 0.0048 | G15: 10675690 | H15: 0.0123 | I15: 19923176 | J15: 0.0116 | K15: 20451705 | L15: 0.0065 | M15: 11895702 | N15: 0.0189 | O15: 36410212 | P15: 0.0084 | Q15: 19768730 | R15: 0.0149 | S15: 28848049 | T15: =U15/$U$9 -> 0.00057146937 | U15: =76179+1002800 -> 1078979 | V15: =W15/$W$10 -> 0.017616062 | W15: =56286+32677200 -> 32733486 | X15: =Y15/$Y$10 -> 0.0027824887 | Y15: =41188+7018920 -> 7060108 | Z15: =AA15/$AA$10 -> 0.005373077 | AA15: =32853+13197181 -> 13230034 | AC15: 1020420 | AD15: =E15/$E$9 -> 0.0085657253 | AF15: Net Earning Nov | AG15: =AG13-AG14 -> 207642852
A16: 711.1 | B16: Thu từ khấu trừ thuế CTV | E16: =G16+I16+K16+M16+O16+Q16+S16+U16+W16+Y16+AA16+AC16 -> 15800000 | F16: 0 | G16: 0 | H16: 0 | I16: 0 | J16: 0 | K16: 0 | L16: 0 | M16: 0 | N16: 0 | O16: 0 | P16: 0 | Q16: 0 | R16: 0 | S16: 0 | T16: =U16/$U$9 -> 0.0012181697 | U16: 2300000 | V16: =W16/$W$10 -> 0.0011839661 | W16: 2200000 | X16: =Y16/$Y$10 -> 0.0027193878 | Y16: 6900000 | Z16: =AA16/$AA$10 -> 0.00093409262 | AA16: 2300000 | AC16: 2100000 | AD16: =E16/$E$9 -> 0.00066637583 | AF16: Total Income 2024 | AG16: =E9 -> 23710343643
A17: 515.1-635.1 | B17: Lãi/lỗ TG | C17: Lãi/lỗ TG thanh toán | E17: =G17+I17+K17+M17+O17+Q17+S17+U17+W17+Y17+AA17+AC17 -> 379596 | F17: 0 | G17: 0 | H17: 0 | I17: 0 | J17: 0 | K17: 0 | L17: 0 | M17: 0 | N17: 0 | O17: 0 | P17: 0 | Q17: 0 | R17: 0 | S17: 0 | T17: =U17/$U$9 -> -0.0052347317 | U17: =770240-10653824 -> -9883584 | V17: =W17/$W$10 -> -0.0060725452 | W17: -11283769 | X17: =Y17/$Y$10 -> 0.0059511935 | Y17: =28656582 -13556406 -> 15100176 | Z17: =AA17/$AA$10 -> 0.0026157733 | AA17: =6559263-118490 -> 6440773 | AC17: 6000 | AD17: =E17/$E$9 -> 1.6009722e-05 | AF17: Total Expense 2024 | AG17: =E19 -> 22553248027
A18: 515.4-635.2 | C18: Lãi/lỗ TG rút tiền | E18: =G18+I18+K18+M18+O18+Q18+S18+U18+W18+Y18+AA18+AC18 -> 48230807 | G18: 4984980 | I18: 7721600 | K18: 24515214 | M18: 14392840 | N18: 0 | O18: 6952570 | P18: 0 | Q18: 0 | R18: 0.004 | S18: 7698290 | T18: =U18/$U$9 -> -0.019262927 | U18: -36369917 | V18: =W18/$W$10 -> 0 | W18: 0 | X18: =Y18/$Y$10 -> -0.0014090843 | Y18: -3575320 | Z18: =AA18/$AA$10 -> 0.0074290238 | AA18: =18499720-207364 -> 18292356 | AC18: =5965041-2346847 -> 3618194 | AD18: =E18/$E$9 -> 0.0020341674 | AF18: Net Earning 2024 | AG18: =AG16-AG17 -> 1157095616
B19: CHI | E19: =G19+I19+K19+M19+O19+Q19+S19+U19+W19+Y19+AA19+AC19 -> 22553248027 | G19: =SUBTOTAL(9,G20:G67) -> 1722516041 | I19: =SUBTOTAL(9,I20:I67) -> 2363704252 | K19: =SUBTOTAL(9,K20:K67) -> 1559834918 | M19: =SUBTOTAL(9,M20:M67) -> 1690595966 | O19: =SUBTOTAL(9,O20:O67) -> 1861639598 | Q19: =SUBTOTAL(9,Q20:Q67) -> 1499603845 | S19: =SUBTOTAL(9,S20:S67) -> 1701359420 | U19: =SUBTOTAL(9,U20:U67) -> 2161714351 | W19: =SUBTOTAL(9,W20:W67) -> 1711897855 | X19: =SUBTOTAL(9,X20:X67) -> 0.8877804 | Y19: =SUBTOTAL(9,Y20:Y67) -> 2252596954 | AA19: =SUBTOTAL(9,AA20:AA67) -> 2309047690 | AC19: =SUBTOTAL(9,AC20:AC67) -> 1718737137
B20: Lương dự án | D20: =E20/$E$10 -> 0.53894405 | E20: =G20+I20+K20+M20+O20+Q20+S20+U20+W20+Y20+AA20+AC20 -> 12080946836 | F20: 0.4572 | G20: =SUBTOTAL(9,G21:G25) -> 1020907859 | H20: =SUBTOTAL(9,H21:H25) -> 0.5814 | I20: =SUBTOTAL(9,I21:I25) -> 941315262 | J20: =SUBTOTAL(9,J21:J25) -> 0.4645 | K20: =SUBTOTAL(9,K21:K25) -> 819692583 | L20: =SUBTOTAL(9,L21:L25) -> 0.4697 | M20: =SUBTOTAL(9,M21:M25) -> 859451950 | N20: =SUBTOTAL(9,N21:N25) -> 0.4673 | ... U20: =SUBTOTAL(9,U21:U25) -> 1047255037 | V20: =W20/$W$10 -> 0.52737567 | W20: =SUBTOTAL(9,W21:W25) -> 979949099 | X20: =SUBTOTAL(9,X21:X25) -> 0.4626142 | Y20: =SUBTOTAL(9,Y21:Y25) -> 1173807557 | Z20: =AA20/$AA$10 -> 0.48473517 | AA20: =SUBTOTAL(9,AA21:AA25) -> 1193554971 | AB20: =SUBTOTAL(9,AB21:AB25) -> 0 | AC20: =SUBTOTAL(9,AC21:AC25) -> 1228326323 | AD20: =E20/$E$9 -> 0.50952222
B21: 334.1 | C21: Lương nhân viên nội bộ | D21: =E21/$E$10 -> 0.24440532 | E21: =G21+I21+K21+M21+O21+Q21+S21+U21+W21+Y21+AA21+AC21 -> 5478579104 | F21: 0.1787 | G21: 399102045 | H21: 0.2125 | I21: 344041300 | J21: 0.2085 | K21: 367916299 | L21: 0.2311 | M21: 422918183 | N21: 0.2301 | O21: 442561022 | P21: 0.1887 | Q21: 443212265 | R21: 0.2602 | S21: 504052512 | T21: =U21/$U$9 -> 0.27323221 | U21: 515883846 | V21: =W21/$W$10 -> 0.27863768 | W21: 517753781 | X21: =Y21/$Y$10 -> 0.20392936 | Y21: 517437257 | Z21: =AA21/$AA$10 -> 0.20873539 | AA21: 513965519 | AC21: 489735075 | AD21: =E21/$E$9 -> 0.23106283
B22: 334.2 | C22: Lương nhân viên thuê ngoài trực tiếp (freelancer) | D22: =E22/$E$10 -> 0.12773717 | E22: =G22+I22+K22+M22+O22+Q22+S22+U22+W22+Y22+AA22+AC22 -> 2863350893 | F22: 0.1273 | G22: 284173664 | H22: 0.1846 | I22: 298908567 | J22: 0.1015 | K22: 179163970 | L22: 0.097 | M22: 177453906 | N22: 0.0931 | O22: 179162272 | P22: 0.0738 | Q22: 173300259 | R22: 0.1238 | S22: 239798988 | T22: =U22/$U$9 -> 0.1050325 | U22: 198309593 | V22: =W22/$W$10 -> 0.1085338 | W22: 201673318 | X22: =Y22/$Y$10 -> 0.12127313 | Y22: 307710648 | Z22: =AA22/$AA$10 -> 0.13972669 | AA22: 344046603 | AC22: =12000000+267649105 -> 279649105 | AD22: =E22/$E$9 -> 0.12076379
B23: 331 | C23: Lương nhân viên thuê nhà cung cấp (vendor) | D23: =E23/$E$10 -> 0.15826511 | E23: =G23+I23+K23+M23+O23+Q23+S23+U23+W23+Y23+AA23+AC23 -> 3547664035 | F23: 0.1392 | G23: 310918810 | H23: 0.1748 | I23: 282992152 | J23: 0.1175 | K23: 207310304 | L23: 0.1416 | M23: 259079861 | N23: 0.132 | O23: 253971632 | P23: 0.1276 | Q23: 299704745 | R23: 0.1326 | S23: 256829500 | T23: =U23/$U$9 -> 0.16227949 | U23: 306396398 | V23: =W23/$W$10 -> 0.14020418 | W23: 260522000 | X23: =Y23/$Y$10 -> 0.1299401 | Y23: =374939747-45238095 -> 329701652 | Z23: =AA23/$AA$10 -> 0.13584625 | AA23: 334491849 | AC23: =50000000+395745132 -> 445745132 | AD23: =E23/$E$9 -> 0.14962516
B24: 6421-17 | C24: Chi phí đầu tư đào tạo nhân lực (cử đi đào tạo, học tiếng anh...) | D24: =E24/$E$10 -> 0.0014852366 | E24: =G24+I24+K24+M24+O24+Q24+S24+U24+W24+Y24+AA24+AC24 -> 33293000 | F24: 0 | G24: 0 | H24: 0.0062 | I24: 10000000 | J24: 0 | K24: 0 | L24: 0 | M24: 0 | N24: 0.0121 | O24: 23293000 | P24: 0 | Q24: 0 | R24: 0 | S24: 0 | T24: =U24/$U$9 -> 0 | U24: 0 | V24: =W24/$W$10 -> 0 | X24: =Y24/$Y$10 -> 0 | Z24: =AA24/$AA$10 -> 0 | AD24: =E24/$E$9 -> 0.0014041551
B25: 154 | C25: Chi phí công tác, công cụ, sự kiện dành cho team dự án | D25: =E25/$E$10 -> 0.0070512181 | E25: =G25+I25+K25+M25+O25+Q25+S25+U25+W25+Y25+AA25+AC25 -> 158059804 | F25: 0.012 | G25: 26713340 | H25: 0.0033 | I25: 5373243 | J25: 0.037 | K25: 65302010 | L25: 0 | M25: 0 | N25: 0 | O25: 0 | P25: 0 | Q25: 0 | R25: 0.0004 | S25: 800000 | T25: =U25/$U$9 -> 0.01412293 | U25: 26665200 | V25: =W25/$W$10 -> 0 | X25: =Y25/$Y$10 -> 0.0074716166 | Y25: 18958000 | Z25: =AA25/$AA$10 -> 0.00042683972 | AA25: 1051000 | AC25: 13197011 | AD25: =E25/$E$9 -> 0.0066662806
B26: Quản lý văn phòng | D26: =E26/$E$10 -> 0.065909906 | E26: =G26+I26+K26+M26+O26+Q26+S26+U26+W26+Y26+AA26+AC26 -> 1477433628 | F26: 0.0065 | G26: =SUBTOTAL(9,G27:G29) -> 14525138 | H26: =SUBTOTAL(9,H27:H29) -> 0.1741 | I26: =SUBTOTAL(9,I27:I29) -> 281992770 | J26: =SUBTOTAL(9,J27:J29) -> 0.0205 | K26: =SUBTOTAL(9,K27:K29) -> 36173939 | L26: =SUBTOTAL(9,L27:L29) -> 0.0131 | M26: =SUBTOTAL(9,M27:M29) -> 23917338 | N26: =SUBTOTAL(9,N27:N29) -> 0.1593 | ... U26: =SUBTOTAL(9,U27:U29) -> 329763716 | V26: =W26/$W$10 -> 0.011157151 | W26: =SUBTOTAL(9,W27:W29) -> 20731787 | X26: =SUBTOTAL(9,X27:X29) -> 0.027105189 | Y26: =SUBTOTAL(9,Y27:Y29) -> 68774964 | Z26: =AA26/$AA$10 -> 0.1276686 | AA26: =SUBTOTAL(9,AA27:AA29) -> 314356168 | AB26: =SUBTOTAL(9,AB27:AB29) -> 0 | AC26: =SUBTOTAL(9,AC27:AC29) -> 22771335 | AD26: =E26/$E$9 -> 0.062311776
A27: chia theo pbo | B27: 242 | C27: Chi phí thuê nhà | D27: =E27/$E$10 -> 0.050957538 | E27: =G27+I27+K27+M27+O27+Q27+S27+U27+W27+Y27+AA27+AC27 -> 1142262000 | F27: 0 | G27: 0 | H27: 0.1664 | I27: 269505600 | J27: 0.006 | K27: 10560000 | L27: 0 | M27: 0 | N27: 0.1447 | O27: 278230680 | P27: 0 | Q27: 0 | R27: 0 | S27: 0 | T27: =U27/$U$9 -> 0.15646861 | U27: 295425000 | V27: =W27/$W$10 -> 0 | X27: =Y27/$Y$10 -> 0 | Z27: =AA27/$AA$10 -> 0.11718424 | AA27: 288540720 | AD27: =E27/$E$9 -> 0.048175683
B28: 6422.2 | C28: Dịch vụ/Điện/Nước/Gửi xe... | D28: =E28/$E$10 -> 0.01024912 | E28: =G28+I28+K28+M28+O28+Q28+S28+U28+W28+Y28+AA28+AC28 -> 229743836 | F28: 0.006 | G28: 13452448 | H28: 0.0073 | I28: 11852360 | J28: 0.0072 | K28: 12704505 | L28: 0.0095 | M28: 17377870 | N28: 0.0109 | O28: 21000714 | P28: 0.0099 | Q28: 23204393 | R28: 0.0115 | S28: 22245946 | T28: =U28/$U$9 -> 0.012098649 | U28: 22843199 | V28: =W28/$W$10 -> 0.011013417 | W28: 20464707 | X28: =Y28/$Y$10 -> 0.008350479 | Y28: 21187969 | Z28: =AA28/$AA$10 -> 0.0084107832 | AA28: 20709725 | AC28: =1700000+21000000 -> 22700000 | AD28: =E28/$E$9 -> 0.0096896038
B29: 6422.3 | C29: Chi phí mua sắm, phục vụ văn phòng cơ bản | D29: =E29/$E$10 -> 0.0047032474 | E29: =G29+I29+K29+M29+O29+Q29+S29+U29+W29+Y29+AA29+AC29 -> 105427792 | F29: 0.0005 | G29: 1072690 | H29: 0.0004 | I29: 634810 | J29: 0.0073 | K29: 12909434 | L29: 0.0036 | M29: 6539468 | N29: 0.0037 | O29: 7085360 | P29: 0.0007 | Q29: 1554580 | R29: 0.0057 | S29: 11104800 | T29: =U29/$U$9 -> 0.0060884743 | U29: 11495517 | V29: =W29/$W$10 -> 0.00014373348 | W29: 267080 | X29: =Y29/$Y$10 -> 0.01875471 | Y29: =45720000+1866995 -> 47586995 | Z29: =AA29/$AA$10 -> 0.0020735731 | AA29: 5105723 | AC29: 71335 | AD29: =E29/$E$9 -> 0.0044464894
B30: Chi phí đảm bảo chất lượng | D30: =E30/$E$10 -> 0.0022376024 | E30: =G30+I30+K30+M30+O30+Q30+S30+U30+W30+Y30+AA30+AC30 -> 50158000 | F30: 0.0027 | G30: =SUBTOTAL(9,G31:G32) -> 6000000 | H30: =SUBTOTAL(9,H31:H32) -> 0.0037 | I30: =SUBTOTAL(9,I31:I32) -> 6000000 | J30: =SUBTOTAL(9,J31:J32) -> 0.0181 | K30: =SUBTOTAL(9,K31:K32) -> 31900000 | L30: =SUBTOTAL(9,L31:L32) -> 0 | M30: =SUBTOTAL(9,M31:M32) -> 0 | N30: =SUBTOTAL(9,N31:N32) -> 0 | ... U30: =SUBTOTAL(9,U31:U32) -> 6000000 | V30: =W30/$W$10 -> 0 | W30: =SUBTOTAL(9,W31:W32) -> 0 | X30: =SUBTOTAL(9,X31:X32) -> 0 | Y30: =SUBTOTAL(9,Y31:Y32) -> 0 | Z30: =AA30/$AA$10 -> 0 | AA30: =SUBTOTAL(9,AA31:AA32) -> 0 | AB30: =SUBTOTAL(9,AB31:AB32) -> 0 | AC30: =SUBTOTAL(9,AC31:AC32) -> 0 | AD30: =E30/$E$9 -> 0.002115448
B31: 6421.1 | C31: ISO | D31: =E31/$E$10 -> 0.00053533293 | E31: =G31+I31+K31+M31+O31+Q31+S31+U31+W31+Y31+AA31+AC31 -> 12000000 | F31: 0.0027 | G31: 6000000 | H31: 0.0037 | I31: 6000000 | J31: 0 | K31: 0 | L31: 0 | M31: 0 | N31: 0 | O31: 0 | P31: 0 | Q31: 0 | R31: 0 | S31: 0 | T31: =U31/$U$9 -> 0 | U31: 0 | V31: =W31/$W$10 -> 0 | X31: =Y31/$Y$10 -> 0 | Z31: =AA31/$AA$10 -> 0 | AD31: =E31/$E$9 -> 0.00050610823
B32: 6422.4 | C32: Chi phí quản lý | D32: =E32/$E$10 -> 0.0017022695 | E32: =G32+I32+K32+M32+O32+Q32+S32+U32+W32+Y32+AA32+AC32 -> 38158000 | F32: 0 | G32: 0 | H32: 0 | I32: 0 | J32: 0.0181 | K32: 31900000 | L32: 0 | M32: 0 | N32: 0 | O32: 0 | P32: 0.0001 | Q32: 258000 | R32: 0 | S32: 0 | T32: =U32/$U$9 -> 0.0031778341 | U32: 6000000 | V32: =W32/$W$10 -> 0 | X32: =Y32/$Y$10 -> 0 | Z32: =AA32/$AA$10 -> 0 | AD32: =E32/$E$9 -> 0.0016093398
B33: Hành chính/ Nhân Sự | D33: =E33/$E$10 -> 0.043375899 | E33: =G33+I33+K33+M33+O33+Q33+S33+U33+W33+Y33+AA33+AC33 -> 972312294 | F33: 0.0192 | G33: =SUBTOTAL(9,G34:G35) -> 42881806 | H33: =SUBTOTAL(9,H34:H35) -> 0.0278 | I33: =SUBTOTAL(9,I34:I35) -> 44977675 | J33: =SUBTOTAL(9,J34:J35) -> 0.0322 | K33: =SUBTOTAL(9,K34:K35) -> 56896750 | L33: =SUBTOTAL(9,L34:L35) -> 0.0318 | M33: =SUBTOTAL(9,M34:M35) -> 58183538 | N33: =SUBTOTAL(9,N34:N35) -> 0.0238 | ... U33: =SUBTOTAL(9,U34:U35) -> 54085380 | V33: =W33/$W$10 -> 0.041196856 | W33: =SUBTOTAL(9,W34:W35) -> 76550406 | X33: =SUBTOTAL(9,X34:X35) -> 0.087048694 | Y33: =SUBTOTAL(9,Y34:Y35) -> 220871764 | Z33: =AA33/$AA$10 -> 0.061589954 | AA33: =SUBTOTAL(9,AA34:AA35) -> 151651871 | AB33: =SUBTOTAL(9,AB34:AB35) -> 0 | AC33: =SUBTOTAL(9,AC34:AC35) -> 96263350 | AD33: =E33/$E$9 -> 0.041007938
A34: 6421.2 | B34: 334.5 | C34: Lương/Thưởng cho bộ phận HCNS | D34: =E34/$E$10 -> 0.017528456 | E34: =G34+I34+K34+M34+O34+Q34+S34+U34+W34+Y34+AA34+AC34 -> 392917120 | F34: 0.0154 | G34: 34465550 | H34: 0.0206 | I34: 33377875 | J34: 0.0195 | K34: 34465550 | L34: 0.0189 | M34: 34529000 | N34: 0.018 | O34: 34529000 | P34: 0.0147 | Q34: 34529000 | R34: 0.0144 | S34: 27960594 | T34: =U34/$U$9 -> 0.01307434 | U34: 24685380 | V34: =W34/$W$10 -> 0.017238764 | W34: 32032406 | X34: =Y34/$Y$10 -> 0.012870218 | Y34: 32656064 | Z34: =AA34/$AA$10 -> 0.014150834 | AA34: 34843351 | AC34: 34843350 | AD34: =E34/$E$9 -> 0.016571549
B35: 6422.5 | C35: Các chi phí hoạt động nội bộ | D35: =E35/$E$10 -> 0.025847443 | E35: =G35+I35+K35+M35+O35+Q35+S35+U35+W35+Y35+AA35+AC35 -> 579395174 | F35: 0.0038 | G35: 8416256 | H35: 0.0072 | I35: 11599800 | J35: 0.0127 | K35: 22431200 | L35: 0.0129 | M35: 23654538 | N35: 0.0058 | O35: 11166000 | P35: 0.0032 | Q35: 7500000 | R35: 0.028 | S35: 54265160 | T35: =U35/$U$9 -> 0.015571387 | U35: 29400000 | V35: =W35/$W$10 -> 0.023958091 | W35: 44518000 | X35: =Y35/$Y$10 -> 0.074178476 | Y35: 188215700 | Z35: =AA35/$AA$10 -> 0.04743912 | AA35: 116808520 | AC35: =16520000+24900000+20000000 -> 61420000 | AD35: =E35/$E$9 -> 0.024436389
B36: Kế toán/Tài Chính | D36: =E36/$E$10 -> 0.019442578 | E36: =G36+I36+K36+M36+O36+Q36+S36+U36+W36+Y36+AA36+AC36 -> 435824000 | F36: 0.02 | G36: =SUBTOTAL(9,G37:G38) -> 44604500 | H36: =SUBTOTAL(9,H37:H38) -> 0.0209 | I36: =SUBTOTAL(9,I37:I38) -> 33864500 | J36: =SUBTOTAL(9,J37:J38) -> 0.0187 | K36: =SUBTOTAL(9,K37:K38) -> 33029000 | L36: =SUBTOTAL(9,L37:L38) -> 0.0182 | M36: =SUBTOTAL(9,M37:M38) -> 33409000 | N36: =SUBTOTAL(9,N37:N38) -> 0.0172 | ... U36: =SUBTOTAL(9,U37:U38) -> 37466000 | V36: =W36/$W$10 -> 0.020162942 | W36: =SUBTOTAL(9,W37:W38) -> 37466000 | X36: =SUBTOTAL(9,X37:X38) -> 0.014765882 | Y36: =SUBTOTAL(9,Y37:Y38) -> 37466000 | Z36: =AA36/$AA$10 -> 0.015215963 | AA36: =SUBTOTAL(9,AA37:AA38) -> 37466000 | AB36: =SUBTOTAL(9,AB37:AB38) -> 0 | AC36: =SUBTOTAL(9,AC37:AC38) -> 37466000 | AD36: =E36/$E$9 -> 0.018381176
A37: 6422.6 | B37: 334.3 | C37: Lương bộ phận kế toán | D37: =E37/$E$10 -> 0.018919736 | E37: =G37+I37+K37+M37+O37+Q37+S37+U37+W37+Y37+AA37+AC37 -> 424104000 | F37: 0.0149 | G37: 33264500 | H37: 0.0209 | I37: 33864500 | J37: 0.0187 | K37: 33029000 | L37: 0.018 | M37: 33029000 | N37: 0.0172 | O37: 33029000 | P37: 0.0141 | Q37: 33029000 | R37: 0.0194 | S37: 37529000 | T37: =U37/$U$9 -> 0.019843455 | U37: 37466000 | V37: =W37/$W$10 -> 0.020162942 | W37: 37466000 | X37: =Y37/$Y$10 -> 0.014765882 | Y37: 37466000 | Z37: =AA37/$AA$10 -> 0.015215963 | AA37: 37466000 | AC37: 37466000 | AD37: =E37/$E$9 -> 0.017886877
B38: 6422.7 | C38: Chi phí xử lý thuế, các vấn đề về kế toán (nếu có) | D38: =E38/$E$10 -> 0.00052284182 | E38: =G38+I38+K38+M38+O38+Q38+S38+U38+W38+Y38+AA38+AC38 -> 11720000 | F38: 0.0051 | G38: 11340000 | H38: 0 | I38: 0 | J38: 0 | K38: 0 | L38: 0.0002 | M38: 380000 | N38: 0 | O38: 0 | P38: 0 | Q38: 0 | R38: 0 | S38: 0 | T38: =U38/$U$9 -> 0 | U38: 0 | V38: =W38/$W$10 -> 0 | X38: =Y38/$Y$10 -> 0 | Z38: =AA38/$AA$10 -> 0 | AD38: =E38/$E$9 -> 0.00049429904
B39: Sales | D39: =E39/$E$10 -> 0.071045877 | E39: =G39+I39+K39+M39+O39+Q39+S39+U39+W39+Y39+AA39+AC39 -> 1592561346 | F39: 0.0247 | G39: =SUBTOTAL(9,G40:G45) -> 55247392 | H39: =SUBTOTAL(9,H40:H45) -> 0.045 | I39: =SUBTOTAL(9,I40:I45) -> 72806980 | J39: =SUBTOTAL(9,J40:J45) -> 0.0749 | K39: =SUBTOTAL(9,K40:K45) -> 132411151 | L39: =SUBTOTAL(9,L40:L45) -> 0.0656 | M39: =SUBTOTAL(9,M40:M45) -> 120029622 | N39: =SUBTOTAL(9,N40:N45) -> 0.07 | ... U39: =SUBTOTAL(9,U40:U45) -> 178795376 | V39: =W39/$W$10 -> 0.10762058 | W39: =SUBTOTAL(9,W40:W45) -> 199976404 | X39: =SUBTOTAL(9,X40:X45) -> 0.075991742 | Y39: =SUBTOTAL(9,Y40:Y45) -> 192816565 | Z39: =AA39/$AA$10 -> 0.063668349 | AA39: =SUBTOTAL(9,AA40:AA45) -> 156769467 | AB39: =SUBTOTAL(9,AB40:AB45) -> 0 | AC39: =SUBTOTAL(9,AC40:AC45) -> 150480593 | AD39: =E39/$E$9 -> 0.067167367 | AE39: =8/100*E10 -> 1793276582 | AF39: =AE39-E39-E46 -> -181542357
A40: 6421.3 | B40: 334.6 | C40: Lương NV Sales | D40: =E40/$E$10 -> 0.033827591 | E40: =G40+I40+K40+M40+O40+Q40+S40+U40+W40+Y40+AA40+AC40 -> 758277843 | F40: 0.0108 | G40: 24115000 | H40: 0.015 | I40: 24256000 | J40: 0.0228 | K40: 40243750 | L40: 0.0275 | M40: 50244750 | N40: 0.0271 | O40: 52159046 | P40: 0.024 | Q40: 56334044 | R40: 0.0356 | S40: 69056775 | T40: =U40/$U$9 -> 0.039998679 | U40: =51405643+24115000 -> 75520643 | V40: =W40/$W$10 -> 0.051317993 | W40: =58867113 +24115000+12375000 -> 95357113 | X40: =Y40/$Y$10 -> 0.038117738 | Y40: =60227500+36490000 -> 96717500 | Z40: =AA40/$AA$10 -> 0.034904424 | AA40: =61829556+24115000 -> 85944556 | AC40: 88328666 | AD40: =E40/$E$9 -> 0.031980888
A41: 6421.4 | C41: Công cụ phục vụ Sales | D41: =E41/$E$10 -> 0.0041686025 | E41: =G41+I41+K41+M41+O41+Q41+S41+U41+W41+Y41+AA41+AC41 -> 93443216 | F41: 0 | G41: 0 | H41: 0.0021 | I41: 3345630 | J41: 0.0056 | K41: 9918031 | L41: 0.015 | M41: 27540313 | N41: 0.0032 | O41: 6208036 | P41: 0.0046 | Q41: 10765578 | R41: 0.0047 | S41: 9148421 | T41: =U41/$U$9 -> 0.0033912463 | U41: 6402939 | V41: =W41/$W$10 -> 0.0021048274 | W41: 3911109 | X41: =Y41/$Y$10 -> 0.0033257396 | Y41: 8438518 | Z41: =AA41/$AA$10 -> 0.0030307817 | AA41: 7462641 | AC41: 302000 | AD41: =E41/$E$9 -> 0.0039410317
A42: 6421.5 | C42: Tiếp khách | D42: =E42/$E$10 -> 0.00083020528 | E42: =G42+I42+K42+M42+O42+Q42+S42+U42+W42+Y42+AA42+AC42 -> 18609846 | F42: 0.0035 | G42: 7832392 | H42: 0.0003 | I42: 515500 | J42: 0.0011 | K42: 1969378 | L42: 0.0001 | M42: 108270 | N42: 0 | O42: 0 | P42: 0.0015 | Q42: 3544381 | R42: 0 | S42: 60000 | T42: =U42/$U$9 -> 0.001286508 | U42: 2429028 | V42: =W42/$W$10 -> 0 | X42: =Y42/$Y$10 -> 0 | Z42: =AA42/$AA$10 -> 0.00087353783 | AA42: 2150897 | AD42: =E42/$E$9 -> 0.00078488301
A43: 6421.6 | C43: Công tác (sales) | D43: =E43/$E$10 -> 0.016126913 | E43: =G43+I43+K43+M43+O43+Q43+S43+U43+W43+Y43+AA43+AC43 -> 361500196 | F43: 0 | G43: 0 | H43: 0 | I43: 0 | J43: 0.0152 | K43: 26872992 | L43: 0.0197 | M43: 36088670 | N43: 0.0252 | O43: 48464932 | P43: 0.0056 | Q43: 13049000 | R43: 0.0028 | S43: 5435000 | T43: =U43/$U$9 -> 0.032518141 | U43: =82451476-21054676 -> 61396800 | V43: =W43/$W$10 -> 0.027233235 | W43: =21054676+29549070 -> 50603746 | X43: =Y43/$Y$10 -> 0.020737515 | Y43: 52618039 | Z43: =AA43/$AA$10 -> 0.016311934 | AA43: 40164590 | AC43: =9969427+16837000 -> 26806427 | AD43: =E43/$E$9 -> 0.015246519
A44: 6421.7 | C44: Hội phí tham gia các tổ chức hiệp hội | D44: =E44/$E$10 -> 0.0076253874 | E44: =G44+I44+K44+M44+O44+Q44+S44+U44+W44+Y44+AA44+AC44 -> 170930358 | F44: 0.0025 | G44: 5500000 | H44: 0.0276 | I44: 44689850 | J44: 0.0271 | K44: 47907000 | L44: 0 | M44: 0 | N44: 0.0118 | O44: 22679550 | P44: 0.0001 | Q44: 129000 | R44: 0.004 | S44: 7761045 | T44: =U44/$U$9 -> 0.0040675958 | U44: 7679940 | V44: =W44/$W$10 -> 0.013251246 | W44: 24622954 | X44: =Y44/$Y$10 -> 0.0037720976 | Y44: 9571078 | Z44: =AA44/$AA$10 -> 0.00015836566 | AA44: 389941 | AD44: =E44/$E$9 -> 0.007209105
A45: 154 | C45: Commission_Sales | D45: =E45/$E$10 -> 0.0084671774 | E45: =G45+I45+K45+M45+O45+Q45+S45+U45+W45+Y45+AA45+AC45 -> 189799887 | F45: 0.008 | G45: 17800000 | H45: 0 | I45: 0 | J45: 0.0031 | K45: 5500000 | L45: 0.0033 | M45: 6047619 | N45: 0.0027 | O45: 5141367 | P45: 0.0009 | Q45: 2224640 | R45: 0.0109 | S45: 21066981 | T45: =U45/$U$9 -> 0.013434837 | U45: 25366026 | V45: =W45/$W$10 -> 0.013713277 | W45: 25481482 | X45: =Y45/$Y$10 -> 0.010038652 | Y45: 25471430 | Z45: =AA45/$AA$10 -> 0.008389306 | AA45: 20656842 | AC45: =23977000+8816500+2250000 -> 35043500 | AD45: =E45/$E$9 -> 0.0080049404
B46: Marketing | D46: =E46/$E$10 -> 0.017052923 | E46: =G46+I46+K46+M46+O46+Q46+S46+U46+W46+Y46+AA46+AC46 -> 382257593 | F46: 0.0194 | G46: =SUBTOTAL(9,G47:G50) -> 43375871 | H46: =SUBTOTAL(9,H47:H50) -> 0.0374 | I46: =SUBTOTAL(9,I47:I50) -> 60474882 | J46: =SUBTOTAL(9,J47:J50) -> 0.0259 | K46: =SUBTOTAL(9,K47:K50) -> 45711639 | L46: =SUBTOTAL(9,L47:L50) -> 0.0174 | M46: =SUBTOTAL(9,M47:M50) -> 31961833 | N46: =SUBTOTAL(9,N47:N50) -> 0.0167 | ... U46: =SUBTOTAL(9,U47:U50) -> 14040538 | V46: =W46/$W$10 -> 0.011620031 | W46: =SUBTOTAL(9,W47:W50) -> 21591892 | X46: =SUBTOTAL(9,X47:X50) -> 0.011283184 | Y46: =SUBTOTAL(9,Y47:Y50) -> 28629226 | Z46: =AA46/$AA$10 -> 0.012658798 | AA46: =SUBTOTAL(9,AA47:AA50) -> 31169537 | AB46: =SUBTOTAL(9,AB47:AB50) -> 0 | AC46: =SUBTOTAL(9,AC47:AC50) -> 25505267 | AD46: =E46/$E$9 -> 0.016121976
A47: 6421-15 | B47: 334.7 | C47: Lương NV Marketing | D47: =E47/$E$10 -> 0.014131934 | E47: =G47+I47+K47+M47+O47+Q47+S47+U47+W47+Y47+AA47+AC47 -> 316780818 | F47: 0.0193 | G47: 43093171 | H47: 0.0285 | I47: 46081193 | J47: 0.0208 | K47: 36636121 | L47: 0.0118 | M47: 21631381 | N47: 0.0116 | O47: 22329000 | P47: 0.0078 | Q47: 18435153 | R47: 0.0107 | S47: 20693925 | T47: =U47/$U$9 -> 0.0070459891 | U47: 13303380 | V47: =W47/$W$10 -> 0.010719932 | W47: 19919364 | X47: =Y47/$Y$10 -> 0.0090221509 | Y47: 22892226 | Z47: =AA47/$AA$10 -> 0.010732171 | AA47: 26425637 | AC47: 25340267 | AD47: =E47/$E$9 -> 0.013360448
A48: 6421.8 | C48: Công tác (team marketing) | D48: =E48/$E$10 -> 0 | E48: =G48+I48+K48+M48+O48+Q48+S48+U48+W48+Y48+AA48+AC48 -> 0 | F48: 0 | G48: 0 | H48: 0 | I48: 0 | J48: 0 | K48: 0 | L48: 0 | M48: 0 | N48: 0 | O48: 0 | P48: 0 | Q48: 0 | R48: 0 | S48: 0 | T48: =U48/$U$9 -> 0 | V48: =W48/$W$10 -> 0 | X48: =Y48/$Y$10 -> 0 | Z48: =AA48/$AA$10 -> 0 | AD48: =E48/$E$9 -> 0
A49: 6421.9 | C49: Event marketing | D49: =E49/$E$10 -> 7.8337052e-06 | E49: =G49+I49+K49+M49+O49+Q49+S49+U49+W49+Y49+AA49+AC49 -> 175600 | F49: 0 | G49: 0 | H49: 0.0001 | I49: 175600 | J49: 0 | K49: 0 | L49: 0 | M49: 0 | N49: 0 | O49: 0 | P49: 0 | Q49: 0 | R49: 0 | S49: 0 | T49: =U49/$U$9 -> 0 | V49: =W49/$W$10 -> 0 | X49: =Y49/$Y$10 -> 0 | Z49: =AA49/$AA$10 -> 0 | AD49: =E49/$E$9 -> 7.4060504e-06
A50: 1651537 | C50: Các CP khác (hạ tầng, công cụ phục vụ...) (team marketing) | D50: =E50/$E$10 -> 0.0029131558 | E50: =G50+I50+K50+M50+O50+Q50+S50+U50+W50+Y50+AA50+AC50 -> 65301175 | F50: 0.0001 | G50: 282700 | H50: 0.0088 | I50: 14218089 | J50: 0.0051 | K50: 9075518 | L50: 0.0056 | M50: 10330452 | N50: 0.0051 | O50: 9808112 | P50: 0.0021 | Q50: 5008418 | R50: 0.0018 | S50: 3522300 | T50: =U50/$U$9 -> 0.00039042764 | U50: 737158 | V50: =W50/$W$10 -> 0.00090009836 | W50: 1672528 | X50: =Y50/$Y$10 -> 0.0022610331 | Y50: 5737000 | Z50: =AA50/$AA$10 -> 0.0019266269 | AA50: 4743900 | AC50: 165000 | AD50: =E50/$E$9 -> 0.0027541218
B51: Hạ tầng IT | D51: =E51/$E$10 -> 0.0075981617 | E51: =G51+I51+K51+M51+O51+Q51+S51+U51+W51+Y51+AA51+AC51 -> 170320069 | F51: 0.0005 | G51: =SUBTOTAL(9,G52:G54) -> 1008108 | H51: =SUBTOTAL(9,H52:H54) -> 0.0003 | I51: =SUBTOTAL(9,I52:I54) -> 495794 | J51: =SUBTOTAL(9,J52:J54) -> 0.0476 | K51: =SUBTOTAL(9,K52:K54) -> 84032547 | L51: =SUBTOTAL(9,L52:L54) -> 0.0045 | M51: =SUBTOTAL(9,M52:M54) -> 8159043 | N51: =SUBTOTAL(9,N52:N54) -> 0.0104 | ... U51: =SUBTOTAL(9,U52:U54) -> 7893096 | V51: =W51/$W$10 -> 0.0017064271 | W51: =SUBTOTAL(9,W52:W54) -> 3170817 | X51: =SUBTOTAL(9,X52:X54) -> 0.0021915842 | Y51: =SUBTOTAL(9,Y52:Y54) -> 5560785 | Z51: =AA51/$AA$10 -> 0.00062901472 | AA51: =SUBTOTAL(9,AA52:AA54) -> 1548812 | AB51: =SUBTOTAL(9,AB52:AB54) -> 0 | AC51: =SUBTOTAL(9,AC52:AC54) -> 0 | AD51: =E51/$E$9 -> 0.0071833657
A52: 1651902 | B52: 1651902 | C52: Chi phí Google Workspace | D52: =E52/$E$10 -> 0.0034869976 | E52: =G52+I52+K52+M52+O52+Q52+S52+U52+W52+Y52+AA52+AC52 -> 78164390 | F52: 0 | G52: 0 | H52: 0 | I52: 0 | J52: 0.042 | K52: 74080000 | L52: 0 | M52: 0 | N52: 0 | O52: 0 | P52: 0 | Q52: 0 | R52: 0 | S52: 0 | T52: =U52/$U$9 -> 0 | U52: 0 | V52: =W52/$W$10 -> 0 | X52: =Y52/$Y$10 -> 0.001609716 | Y52: 4084390 | Z52: =AA52/$AA$10 -> 0 | AD52: =E52/$E$9 -> 0.0032966367
A53: 1651933 | B53: 1651933 | C53: Chi phí thuê Cloud Server (Amazon, DO, Vultr…) | D53: =E53/$E$10 -> 0.0011461335 | E53: =G53+I53+K53+M53+O53+Q53+S53+U53+W53+Y53+AA53+AC53 -> 25691679 | F53: 0.0005 | G53: 1008108 | H53: 0.0003 | I53: 495794 | J53: 0.0006 | K53: 1042547 | L53: 0.0003 | M53: 525043 | N53: 0.0042 | O53: 8010590 | P53: 0.0005 | Q53: 1080042 | R53: 0.0003 | S53: 540435 | T53: =U53/$U$9 -> 0.0041804916 | U53: 7893096 | V53: =W53/$W$10 -> 0.0017064271 | W53: 3170817 | X53: =Y53/$Y$10 -> 0.00014834261 | Y53: 376395 | Z53: =AA53/$AA$10 -> 0.00062901472 | AA53: 1548812 | AD53: =E53/$E$9 -> 0.0010835642
A54: 1651568 | C54: Chi phí đầu tư mua sắm bổ sung máy móc | D54: =E54/$E$10 -> 0.0029650306 | E54: =G54+I54+K54+M54+O54+Q54+S54+U54+W54+Y54+AA54+AC54 -> 66464000 | F54: 0 | G54: 0 | H54: 0 | I54: 0 | J54: 0.005 | K54: 8910000 | L54: 0.0042 | M54: 7634000 | N54: 0.0062 | O54: 11880000 | P54: 0.0151 | Q54: 35390000 | R54: 0.0008 | S54: 1550000 | T54: =U54/$U$9 -> 0 | U54: 0 | V54: =W54/$W$10 -> 0 | X54: =Y54/$Y$10 -> 0.0004335256 | Y54: 1100000 | Z54: =AA54/$AA$10 -> 0 | AD54: =E54/$E$9 -> 0.0028031648
B55: Thuế & Bảo hiểm | D55: =E55/$E$10 -> 0.057909407 | E55: =G55+I55+K55+M55+O55+Q55+S55+U55+W55+Y55+AA55+AC55 -> 1298094801 | F55: 0.0878 | G55: =SUBTOTAL(9,G56:G58) -> 196175290 | H55: =SUBTOTAL(9,H56:H58) -> 0.0272 | I55: =SUBTOTAL(9,I56:I58) -> 44064000 | J55: =SUBTOTAL(9,J56:J58) -> 0.027 | K55: =SUBTOTAL(9,K56:K58) -> 47636657 | L55: =SUBTOTAL(9,L56:L58) -> 0.061 | M55: =SUBTOTAL(9,M56:M58) -> 111561818 | N55: =SUBTOTAL(9,N56:N58) -> 0.0964 | ... U55: =SUBTOTAL(9,U56:U58) -> 179994430 | V55: =W55/$W$10 -> 0.035338158 | W55: =SUBTOTAL(9,W56:W58) -> 65664000 | X55: =SUBTOTAL(9,X56:X58) -> 0.088069515 | Y55: =SUBTOTAL(9,Y56:Y58) -> 223461929 | Z55: =AA55/$AA$10 -> 0.026731494 | AA55: =SUBTOTAL(9,AA56:AA58) -> 65820492 | AB55: =SUBTOTAL(9,AB56:AB58) -> 0 | AC55: =SUBTOTAL(9,AC56:AC58) -> 67392000 | AD55: =E55/$E$9 -> 0.054748038
A56: 3334, 3335, 3339 | C56: Thuế phải đóng | D56: =E56/$E$10 -> 0.025100391 | E56: =G56+I56+K56+M56+O56+Q56+S56+U56+W56+Y56+AA56+AC56 -> 562649301 | F56: 0.0681 | G56: 152111290 | H56: 0 | I56: 0 | J56: 0.0011 | K56: 1940657 | L56: 0.0047 | M56: 8601818 | N56: 0.0691 | O56: 132894685 | P56: 0 | Q56: 0 | R56: 0 | S56: 0 | T56: =U56/$U$9 -> 0.060553856 | U56: 114330430 | V56: =W56/$W$10 -> 0 | X56: =Y56/$Y$10 -> 0.060147313 | Y56: 152613929 | Z56: =AA56/$AA$10 -> 6.3555662e-05 | AA56: 156492 | AD56: =E56/$E$9 -> 0.02373012
A57: 3383 | C57: BHXH | D57: =E57/$E$10 -> 0.030400018 | E57: =G57+I57+K57+M57+O57+Q57+S57+U57+W57+Y57+AA57+AC57 -> 681445500 | F57: 0.0197 | G57: 44064000 | H57: 0.0272 | I57: 44064000 | J57: 0.0259 | K57: 45696000 | L57: 0.0268 | M57: 48960000 | N57: 0.0273 | O57: 52453500 | P57: 0.0222 | Q57: 52224000 | R57: 0.0303 | S57: 58752000 | T57: =U57/$U$9 -> 0.034778216 | U57: 65664000 | V57: =W57/$W$10 -> 0.035338158 | W57: 65664000 | X57: =Y57/$Y$10 -> 0.027922201 | Y57: 70848000 | Z57: =AA57/$AA$10 -> 0.026667938 | AA57: 65664000 | AC57: 67392000 | AD57: =E57/$E$9 -> 0.028740431
A58: 6422.8 | C58: BH Tự nguyện | D58: =E58/$E$10 -> 0.0024089982 | E58: =G58+I58+K58+M58+O58+Q58+S58+U58+W58+Y58+AA58+AC58 -> 54000000 | F58: 0 | G58: 0 | H58: 0 | I58: 0 | J58: 0 | K58: 0 | L58: 0.0295 | M58: 54000000 | N58: 0 | O58: 0 | P58: 0 | Q58: 0 | R58: 0 | S58: 0 | T58: =U58/$U$9 -> 0 | U58: 0 | V58: =W58/$W$10 -> 0 | X58: =Y58/$Y$10 -> 0 | Z58: =AA58/$AA$10 -> 0 | AD58: =E58/$E$9 -> 0.002277487
B59: Thưởng (Bonus) | D59: =E59/$E$10 -> 0.030521987 | E59: =G59+I59+K59+M59+O59+Q59+S59+U59+W59+Y59+AA59+AC59 -> 684179547 | F59: 0.0101 | G59: =SUBTOTAL(9,G60:G64) -> 22565377 | H59: =SUBTOTAL(9,H60:H64) -> 0.3254 | I59: =SUBTOTAL(9,I60:I64) -> 526992689 | J59: =SUBTOTAL(9,J60:J64) -> 0.0064 | K59: =SUBTOTAL(9,K60:K64) -> 11380952 | L59: =SUBTOTAL(9,L60:L64) -> 0.0065 | M59: =SUBTOTAL(9,M60:M64) -> 11809524 | N59: =SUBTOTAL(9,N60:N64) -> 0.0057 | ... U59: =SUBTOTAL(9,U60:U64) -> 13369565 | V59: =W59/$W$10 -> 0.0043053311 | W59: =SUBTOTAL(9,W60:W64) -> 8000000 | X59: =SUBTOTAL(9,X60:X64) -> 0.0044971242 | Y59: =SUBTOTAL(9,Y60:Y64) -> 11410714 | Z59: =AA59/$AA$10 -> 0.0060565437 | AA59: =SUBTOTAL(9,AA60:AA64) -> 14912922 | AB59: =SUBTOTAL(9,AB60:AB64) -> 0 | AC59: =SUBTOTAL(9,AC60:AC64) -> 15734819 | AD59: =E59/$E$9 -> 0.028855741
A60: 334.4 | B60: Thưởng bonus dự án | C60: Thưởng bonus dự án | D60: =E60/$E$10 -> 0.024387276 | E60: =G60+I60+K60+M60+O60+Q60+S60+U60+W60+Y60+AA60+AC60 -> 546664133 | F60: 0.0078 | G60: 17375577 | H60: 0.2578 | I60: 417405745 | J60: 0.0064 | K60: 11380952 | L60: 0.0065 | M60: 11809524 | N60: 0.0057 | O60: 11000000 | P60: 0.0091 | Q60: 21472147 | R60: 0.0057 | S60: 11030838 | T60: =U60/$U$9 -> 0.0036383896 | U60: 6869565 | V60: =W60/$W$10 -> 0.0043053311 | W60: 8000000 | X60: =Y60/$Y$10 -> 0.0044971242 | Y60: 11410714 | Z60: =AA60/$AA$10 -> 0.0022955018 | AA60: 5652174 | AC60: 13256897 | AD60: =E60/$E$9 -> 0.023055935
A61: 334.9 +6421-12 | B61: Thưởng bonus tuyển dụng | C61: Chi phí tuyển dụng (Bonus tuyển dụng, Thuê dịch vụ …) | D61: =E61/$E$10 -> 0.0018459885 | E61: =G61+I61+K61+M61+O61+Q61+S61+U61+W61+Y61+AA61+AC61 -> 41379600 | F61: 0.0023 | G61: 5189800 | H61: 0.0223 | I61: 36189800 | J61: 0 | K61: 0 | L61: 0 | M61: 0 | N61: 0 | O61: 0 | P61: 0 | Q61: 0 | R61: 0 | S61: 0 | T61: =U61/$U$9 -> 0 | U61: 0 | V61: =W61/$W$10 -> 0 | X61: =Y61/$Y$10 -> 0 | Z61: =AA61/$AA$10 -> 0 | AD61: =E61/$E$9 -> 0.001745213
A62: 6421-13 | B62: Thưởng marketing | C62: Thưởng MKT | D62: =E62/$E$10 -> 0.0016934365 | E62: =G62+I62+K62+M62+O62+Q62+S62+U62+W62+Y62+AA62+AC62 -> 37960000 | F62: 0 | G62: 0 | H62: 0.0234 | I62: 37960000 | J62: 0 | K62: 0 | L62: 0 | M62: 0 | N62: 0 | O62: 0 | P62: 0 | Q62: 0 | R62: 0 | S62: 0 | T62: =U62/$U$9 -> 0 | U62: 0 | V62: =W62/$W$10 -> 0 | X62: =Y62/$Y$10 -> 0 | Z62: =AA62/$AA$10 -> 0 | AD62: =E62/$E$9 -> 0.001600989
A63: 6421-14+ 334-11 | B63: Thưởng kinh doanh (sales) | C63: Thưởng kinh doanh | D63: =E63/$E$10 -> 0.0010143966 | E63: =G63+I63+K63+M63+O63+Q63+S63+U63+W63+Y63+AA63+AC63 -> 22738670 | F63: 0 | G63: 0 | H63: 0 | I63: 0 | J63: 0 | K63: 0 | L63: 0 | M63: 0 | N63: 0 | O63: 0 | P63: 0 | Q63: 0 | R63: 0.0023 | S63: 4500000 | T63: =U63/$U$9 -> 0.0034426536 | U63: 6500000 | V63: =W63/$W$10 -> 0 | X63: =Y63/$Y$10 -> 0 | Z63: =AA63/$AA$10 -> 0.0037610419 | AA63: 9260748 | AC63: 2477922 | AD63: =E63/$E$9 -> 0.000959019
A64: 6422.9 + 334-12 | B64: Thưởng kế toán | C64: Thưởng kế toán | D64: =E64/$E$10 -> 0.0015808892 | E64: =G64+I64+K64+M64+O64+Q64+S64+U64+W64+Y64+AA64+AC64 -> 35437144 | F64: 0 | G64: 0 | H64: 0.0219 | I64: 35437144 | J64: 0 | K64: 0 | L64: 0 | M64: 0 | N64: 0 | O64: 0 | P64: 0 | Q64: 0 | R64: 0 | S64: 0 | T64: =U64/$U$9 -> 0 | V64: =W64/$W$10 -> 0 | X64: =Y64/$Y$10 -> 0 | Z64: =AA64/$AA$10 -> 0 | AD64: =E64/$E$9 -> 0.0014945858
A65: 811 | B65: Các khoản chi khác (cho vay, tín dụng,...) | C65: Các khoản chi khác (cho vay, tín dụng,...) | D65: =E65/$E$10 -> 0.0033814712 | E65: =G65+I65+K65+M65+O65+Q65+S65+U65+W65+Y65+AA65+AC65 -> 75798913 | F65: 0.0043 | G65: 9569500 | H65: 0.0167 | I65: 27064500 | J65: 0.0053 | K65: 9314500 | L65: 0.0052 | M65: 9569500 | N65: 0.01 | O65: 19314500 | P65: 0 | Q65: 0 | R65: 0 | S65: 0 | T65: =U65/$U$9 -> 0.00051185003 | U65: 966413 | V65: =W65/$W$10 -> 0 | X65: =Y65/$Y$10 -> 0 | Z65: =AA65/$AA$10 -> 0 | AD65: =E65/$E$10 -> 0.0033814712
A66: 128 | B66: Khoản tiết kiệm | C66: Khoản tiết kiệm | D66: =E66/$E$10 -> 0 | E66: =G66+I66+K66+M66+O66+Q66+S66+U66+W66+Y66+AA66+AC66 -> 0 | F66: 0 | G66: 0 | H66: 0 | I66: 0 | J66: 0 | K66: 0 | L66: 0 | M66: 0 | N66: 0 | O66: 0 | P66: 0 | Q66: 0 | R66: 0 | S66: 0 | T66: =U66/$U$9 -> 0 | U66: 0 | V66: =W66/$W$10 -> 0 | X66: =Y66/$Y$10 -> 0 | Z66: =AA66/$AA$10 -> 0 | AD66: =E66/$E$10 -> 0
A67: 6423-334.8 | B67: Chi chủ sở hữu | C67: Lương/Thưởng cho CSH | D67: =E67/$E$10 -> 0.14870482 | E67: =G67+I67+K67+M67+O67+Q67+S67+U67+W67+Y67+AA67+AC67 -> 3333361000 | F67: 0.119 | G67: 265655200 | H67: 0.1999 | I67: 323655200 | J67: 0.1426 | K67: 251655200 | L67: 0.2309 | M67: 422542800 | N67: 0.0911 | O67: 175267600 | P67: 0.1123 | Q67: 263655200 | R67: 0.1722 | S67: 333655200 | T67: =U67/$U$9 -> 0.15469951 | U67: =74084800+218000000 -> 292084800 | V67: =W67/$W$10 -> 0.16080275 | W67: =74797450 +224000000 -> 298797450 | X67: =Y67/$Y$10 -> 0.11421328 | Y67: =74797450+215000000 -> 289797450 | Z67: =AA67/$AA$10 -> 0.13881325 | AA67: =74797450+267000000 -> 341797450 | AC67: 74797450 | AD67: =E67/$E$10 -> 0.14870482
B68: CUỒI KỲ | G68: 4239048626 | I68: 3522316950 | K68: 3772272859 | M68: 3911889608 | O68: 3973634228 | Q68: 4822733262 | S68: 5058911628 | U68: =U7+(U9-U19) -> 4785275712 | W68: =W7+(W9-W19) -> 4952988949 | X68: =X7+(X9-X19) -> -0.8877804 | Y68: =Y7+(Y9-Y19) -> 5256312713 | AA68: =AA7+(AA9-AA19) -> 5463955565 | AC68: =AC7+(AC9-AC19) -> 3843735303
G70: Jan | I70: Feb | K70: Mar | M70: Apr | O70: May | Q70: Jun | S70: Jul | U70: Aug | W70: Sep | Y70: Oct | AA70: Nov | AC70: Dec
B71: Số dư TK | G71: 4239048626 | I71: 3522316950 | K71: 3772272859 | M71: 3911889609 | O71: 3973634228 | Q71: 4822733263 | S71: 5058911628 | U71: =SUM(U72:U75) -> 4785275712 | W71: =SUM(W72:W75) -> 4952988949 | X71: =SUM(X72:X75) -> 0 | Y71: =SUM(Y72:Y75) -> 5256312713 | AA71: =SUM(AA72:AA75) -> 5463955565 | AC71: =SUM(AC72:AC75) -> 0
B72: 16 | C72: TK Doanh thu | G72: 490000000 | I72: 300000001 | K72: 731002218 | M72: 0 | O72: 0 | Q72: 0 | S72: 8732 | U72: 8439 | W72: 18096 | Y72: 16186139 | AA72: 0
C73: TK tích lũy dự phòng | G73: 2444847573 | I73: 2492520974 | K73: 2420905393 | M73: 2471262885 | O73: 3114233745 | Q73: 4001523701 | S73: 4315405654 | U73: =3067307374 +1717968338 -U72-U74-U75 -> 2914342162 | W73: =3684957358 +1268031591 -W72-W75-W74 -> 3779390889 | Y73: =4362488173 +893824540 -Y72-Y74-Y75 -> 4234992263 | AA73: =4576237614 +887717951 -AA72-AA74-AA75 -> 4495144287
B74: 46 | C74: TK cho CSH | G74: 164240487 | I74: 147570559 | K74: 295982 | M74: 287747364 | O74: 289856202 | Q74: 364705633 | S74: 742713 | U74: 306652782 | W74: 43734239 | Y74: 707682 | AA74: 597740
B75: 28,21,53,Payoneer, vp | C75: TK chi phí | G75: 1139960566 | I75: 582225416 | K75: 620069266 | M75: 1152879360 | O75: 569544281 | Q75: 456503929 | S75: 742754529 | U75: =477690344 +3073595 +367573659 +714930830 +1003901 -> 1564272329 | W75: =930830 +161633357 +161633357 +608916034 +196732147 -> 1129845725 | Y75: =34069694 +722348938 +246559449 +1006241 +442307 -> 1004426629 | AA75: =59587854 +672400635 +234297393 +445812 +1481844 -> 968213538
B76: TÀI KHOẢN NGÂN HÀNG (Ngày 1 hàng tháng) | G76: 4239048626 | I76: 3522316950 | K76: 3772272859 | M76: 3911889609 | O76: 3973634228 | Q76: 4822733263 | S76: 5058911628 | U76: =SUM(U77:U83) -> 4785275712 | W76: =SUM(W77:W83) -> 4952988949 | X76: =SUM(X77:X83) -> 0 | Y76: =SUM(Y77:Y83) -> 5256312713 | Z76: =SUM(Z77:Z83) -> 0 | AA76: =SUM(AA77:AA83) -> 5463955565 | AC76: =SUM(AC77:AC79) -> 0
B77: --Techcombank DN | G77: 1484741710 | I77: 1302804936 | K77: 1054729105 | M77: 1422240951 | O77: 1068247502 | Q77: 714885017 | S77: 137258152 | U77: =1390169611-1003901-714930830 -> 674234880 | W77: =342674695 -1003901 -675502 -> 340995292 | Y77: =264902933 -1006241 -442307 -> 263454385 | AA77: =236823904 -1481844 -445812 -> 234896248
B78: --Techcombank CN | G78: 469215711 | I78: 16470209 | K78: 465077573 | M78: 4690797 | O78: 38651927 | Q78: 105313425 | S78: 31044986 | U78: 3073595 | W78: 223474128 | Y78: 34069694 | AA78: 59587854
B79: --Quy USD-VND | G79: 2285091205 | I79: 2203041805 | K79: 2215285381 | M79: 2416377061 | O79: 2788297199 | Q79: 3907315222 | S79: 4795388739 | U79: =714930830 +327798727 +672066635 +477690344 +1728179343 -> 3920665879 | W79: =1789325314 +797928935 +925354727 +675502 +608916034 -> 4122200512 | Y79: =2077547838 +722348938 +1148276756 +35985870 +628921607 +442307 -> 4613523316 | AA79: =2210565882+1179373253 +31182813 +672400635 +650894047 +445812 -> 4744862442
B80: --GBP | K80: 37180800 | M80: 68580800 | O80: 68580800 | Q80: 68580800 | S80: 68580800 | U80: 68580800 | W80: 68580800 | Y80: 68580800 | AA80: 68580800
B81: --VPBank DN | Q81: 1000383 | S81: 1000535 | U81: 1003901 | W81: 1006070 | Y81: 1006241 | AA81: 1481844
B82: --EUR | O82: 9856800 | Q82: 25638416 | S82: 25638416 | U82: 117716657 | W82: 196732147 | Y82: 275678277 | AA82: 354546377
B83: Tiết kiệm | G83: 0 | I83: 0 | J83: 0 | K83: 0 | L83: 0 | M83: 0 | N83: 0 | O83: 0 | P83: 0 | Q83: 0 | R83: 0 | S83: 0 | T83: 0 | U83: 0 | W83: 0 | X83: 0 | Y83: 0 | AA83: 0

Sheet Project
A1: STT | B1: CÔNG TY | C1: DỰ ÁN | E1: Type | F1: Type | I1: T01 | Q1: T02 | Y1: TỔNG NĂM 2025 | AB1: TỔNG DỰ ÁN | AD1: DỰ ÁN | AK1: T05 | AP1: T06 | AU1: T07 | AZ1: T08 | BE1: T09 | BJ1: T10 | BO1: T11 | BT1: T12 | BY1: TỔNG DỰ ÁN | CA1: DỰ ÁN
F2: Type | H2: DƯ ĐẦU KỲ | I2: Thu | J2: Tạm ứng | K2: Tổng THU | L2: Vendor | M2: Inhouse | N2: CHI KHÔNG THU ĐƯỢC | O2: Tổng CHI | P2: LỖ/LÃI | Q2: Thu | R2: Tạm ứng | S2: Tổng THU | T2: Vendor | U2: Inhouse | V2: CHI KHÔNG THU ĐƯỢC | W2: Tổng CHI | X2: LỖ/LÃI | Y2: THU | Z2: CHI | AA2: LỖ/LÃI | AC2: % | AG2: Tạm ứng | AH2: CHI | AI2: % | AJ2: LỖ/LÃI | AK2: THU | AL2: Tạm ứng | AM2: CHI | AN2: % | AO2: LỖ/LÃI | AP2: THU | AQ2: Tạm ứng | AR2: CHI | AS2: % | AT2: LỖ/LÃI | AU2: THU | AV2: Tạm ứng | AW2: CHI | AX2: % | AY2: LỖ/LÃI | AZ2: THU | BA2: Tạm ứng | BB2: CHI | BC2: % | BD2: LỖ/LÃI | BE2: THU | BF2: Tạm ứng | BG2: CHI | BH2: % | BI2: LỖ/LÃI | BJ2: THU | BK2: Tạm ứng | BL2: CHI | BM2: % | BN2: LỖ/LÃI | BO2: THU | BP2: Tạm ứng | BQ2: CHI | BR2: % | BS2: LỖ/LÃI | BT2: THU | BU2: Tạm ứng | BV2: CHI | BW2: % | BX2: LỖ/LÃI | BZ2: %
A3: 1 | B3: ELMODINO | C3: eShotLink | D3: Completed | E3: T&M | F3: Non-blockchain | G3: =B3&"_"&C3 -> ELMODINO_eShotLink | L3: 0 | O3: 0 | P3: 0 | Q3: 0 | V3: 0 | Z3: 0 | AA3: 0 | AB3: =AA3+H3 -> 0 | AD3: =C3 -> eShotLink | AF3: =Y3/$Y$130 -> #DIV/0! | BY3: =G3+J3 -> #VALUE! | CA3: eShotLink
A4: =IF(C4="","",A3+1) -> 2 | B4: QSOFT | C4: Bluefire AI | D4: On-going | E4: T&M | F4: Non-blockchain | G4: =B4&"_"&C4 -> QSOFT_Bluefire AI | J4: 36467500 | L4: 36467500 | N4: 18937500 | P4: 18937500 | Q4: 17530000 | R4: 0.4807 | T4: 27147149 | V4: 27147149 | X4: 17034000 | Z4: 17034000 | AA4: 10113149 | AB4: =AA4+H4 -> 10113149 | AD4: =C4 -> Bluefire AI | AF4: =Y4/$Y$130 -> #DIV/0! | BY4: =G4+J4 -> #VALUE! | CA4: Bluefire AI
A5: =IF(C5="","",A4+1) -> 3 | C5: ITOP Sensorflow | D5: Completed | E5: T&M | F5: Non-blockchain | G5: =B5&"_"&C5 -> _ITOP Sensorflow | L5: 0 | O5: 0 | P5: 0 | Q5: 0 | V5: 0 | Z5: 0 | AA5: 0 | AB5: =AA5+H5 -> 0 | AD5: =C5 -> ITOP Sensorflow | AF5: =Y5/$Y$130 -> #DIV/0! | BY5: =G5+J5 -> #VALUE! | CA5: ITOP Sensorflow
A6: 2 | C6: ITOP Intribe | D6: Completed | E6: T&M | F6: Non-blockchain | G6: =B6&"_"&C6 -> _ITOP Intribe | L6: 0 | O6: 0 | P6: 0 | Q6: 0 | V6: 0 | Z6: 0 | AA6: 0 | AB6: =AA6+H6 -> 0 | AD6: =C6 -> ITOP Intribe | AF6: =Y6/$Y$130 -> #DIV/0! | BY6: =G6+J6 -> #VALUE! | CA6: ITOP Intribe
A7: =IF(C7="","",A6+1) -> 3 | C7: ITOP Arcanum | D7: Completed | E7: T&M | F7: Non-blockchain | G7: =B7&"_"&C7 -> _ITOP Arcanum | L7: 0 | O7: 0 | P7: 0 | Q7: 0 | V7: 0 | Z7: 0 | AA7: 0 | AB7: =AA7+H7 -> 0 | AD7: =C7 -> ITOP Arcanum | BY7: =G7+J7 -> #VALUE! | CA7: ITOP Arcanum
A8: =IF(C8="","",A7+1) -> 4 | B8: QSOFT | C8: Chocolate | D8: On-going | E8: T&M | F8: Non-blockchain | G8: =B8&"_"&C8 -> QSOFT_Chocolate | I8: 147641943 | J8: 351071139 | L8: 498713082 | M8: 85153193 | N8: 243635500 | P8: 328788693 | Q8: 169924389 | R8: 0.3407 | S8: 115141365 | T8: 263982649 | V8: 379124014 | W8: 82433201 | X8: 182199348 | Z8: 264632549 | AA8: 114491465 | AB8: =AA8+H8 -> 114491465 | AD8: =C8 -> Chocolate | AF8: =Y8/$Y$130 -> #DIV/0! | BY8: =G8+J8 -> #VALUE! | CA8: Chocolate
A9: 3 | B9: VITEX | C9: Vitex | D9: On-going | E9: T&M | F9: Non-blockchain | G9: =B9&"_"&C9 -> VITEX_Vitex | J9: 35000000 | L9: 35000000 | N9: 22000000 | P9: 22000000 | Q9: 13000000 | R9: 0.3714 | T9: 25870000 | V9: 25870000 | X9: 17000000 | Z9: 17000000 | AA9: 8870000 | AB9: =AA9+H9 -> 8870000 | AD9: =C9 -> Vitex | AF9: =Y9/$Y$130 -> #DIV/0! | BY9: =G9+J9 -> #VALUE! | CA9: Vitex
A10: =IF(C10="","",A9+1) -> 4 | B10: VITEX | C10: MGH | D10: Completed | E10: T&M | F10: Blockchain | G10: =B10&"_"&C10 -> VITEX_MGH | I10: 31564000 | L10: 31564000 | M10: 0 | P10: 0 | Q10: 31564000 | R10: 1 | S10: 0 | V10: 0 | Z10: 0 | AA10: 0 | AB10: =AA10+H10 -> 0 | AD10: =C10 -> MGH | BY10: =G10+J10 -> #VALUE! | CA10: MGH
A11: =IF(C11="","",A10+1) -> 5 | B11: VITEX | C11: Xlinq | D11: On-going | E11: T&M | F11: Non-blockchain | G11: =B11&"_"&C11 -> VITEX_Xlinq | J11: 75000000 | L11: 75000000 | N11: 55556500 | P11: 55556500 | Q11: 19443500 | R11: 0.2592 | T11: 55434000 | V11: 55434000 | X11: 41063500 | Z11: 41063500 | AA11: 14370500 | AB11: =AA11+H11 -> 14370500 | AD11: =C11 -> Xlinq | BY11: =G11+J11 -> #VALUE! | CA11: Xlinq
A12: 4 | B12: MintedGEM | C12: MintedGEM | D12: On-going | E12: Fixedprice | F12: Blockchain | G12: =B12&"_"&C12 -> MintedGEM_MintedGEM | L12: 0 | O12: 1467909 | P12: 1467909 | Q12: -1467909 | V12: 0 | Z12: 0 | AA12: 0 | AB12: =AA12+H12 -> 0 | AD12: =C12 -> MintedGEM | AF12: =Y12/$Y$130 -> #DIV/0! | BY12: =G12+J12 -> #VALUE! | CA12: MintedGEM
A13: =IF(C13="","",A12+1) -> 5 | B13: ICE | C13: M&A&Stock Mobile app | D13: Completed | E13: Fixedprice | F13: Non-blockchain | G13: =B13&"_"&C13 -> ICE_M&A&Stock Mobile app | I13: 36000000 | L13: 36000000 | M13: 31405864 | P13: 31405864 | Q13: 4594136 | R13: 0.1276 | V13: 0 | Z13: 0 | AA13: 0 | AB13: =AA13+H13 -> 0 | AD13: =C13 -> M&A&Stock Mobile app | AF13: =Y13/$Y$130 -> #DIV/0! | BY13: =G13+J13 -> #VALUE! | CA13: M&A&Stock Mobile app
A14: =IF(C14="","",A13+1) -> 6 | B14: C2E | C14: C2E | D14: Completed | E14: Fixedprice | F14: Blockchain | G14: =B14&"_"&C14 -> C2E_C2E | L14: 0 | O14: 0 | P14: 0 | Q14: 0 | V14: 0 | Z14: 0 | AA14: 0 | AB14: =AA14+H14 -> 0 | AD14: =C14 -> C2E | AF14: =Y14/$Y$130 -> #DIV/0! | BY14: =G14+J14 -> #VALUE! | CA14: C2E
A15: 5 | B15: Inhouse | C15: Blockchain nội bộ | D15: On-going | F15: Blockchain | G15: =B15&"_"&C15 -> Inhouse_Blockchain nội bộ | L15: 0 | O15: 9613549 | P15: 9613549 | Q15: -9613549 | V15: 0 | Z15: 0 | AA15: 0 | AB15: =AA15+H15 -> 0 | AD15: =C15 -> Blockchain nội bộ | AF15: =Y15/$Y$130 -> #DIV/0! | BY15: =G15+J15 -> #VALUE! | CA15: Blockchain nội bộ
A16: =IF(C16="","",A15+1) -> 6 | C16: Internal NFT WhiteLabel | D16: On-going | F16: Blockchain | G16: =B16&"_"&C16 -> _Internal NFT WhiteLabel | L16: 0 | O16: 0 | P16: 0 | Q16: 0 | V16: 0 | Z16: 0 | AA16: 0 | AB16: =AA16+H16 -> 0 | AD16: =C16 -> Internal NFT WhiteLabel | BY16: =G16+J16 -> #VALUE!
A17: =IF(C17="","",A16+1) -> 7 | C17: ConnectX | D17: On-going | F17: Blockchain | G17: =B17&"_"&C17 -> _ConnectX | L17: 0 | O17: 5393093 | P17: 5393093 | Q17: -5393093 | V17: 0 | Z17: 0 | AA17: 0 | AB17: =AA17+H17 -> 0 | AD17: =C17 -> ConnectX | BY17: =G17+J17 -> #VALUE!
A18: 6 | C18: Sales support | D18: On-going | F18: Non-blockchain | G18: =B18&"_"&C18 -> _Sales support | L18: 0 | O18: 26229818 | P18: 26229818 | Q18: -26229818 | V18: 0 | Z18: 0 | AA18: 0 | AB18: =AA18+H18 -> 0 | AD18: =C18 -> Sales support | BY18: =G18+J18 -> #VALUE!
A19: =IF(C19="","",A18+1) -> 7 | B19: Tiberiu | C19: BRC | D19: Completed | E19: T&M | F19: Non-blockchain | G19: =B19&"_"&C19 -> Tiberiu_BRC | L19: 0 | O19: 0 | P19: 0 | Q19: 0 | V19: 0 | Z19: 0 | AA19: 0 | AB19: =AA19+H19 -> 0 | AD19: =C19 -> BRC | BY19: =G19+J19 -> #VALUE! | CA19: BRC
A20: =IF(C20="","",A19+1) -> 8 | B20: Adam | C20: Crowd Funding | D20: Completed | E20: Fixedprice | F20: Non-blockchain | G20: =B20&"_"&C20 -> Adam_Crowd Funding | L20: 0 | O20: 0 | P20: 0 | Q20: 0 | V20: 0 | Z20: 0 | AA20: 0 | AB20: =AA20+H20 -> 0 | AD20: =C20 -> Crowd Funding | BY20: =G20+J20 -> #VALUE! | CA20: Crowd Funding
A21: 7 | B21: DTS | C21: DTS_01 | D21: Completed | E21: T&M | F21: Non-blockchain | G21: =B21&"_"&C21 -> DTS_DTS_01 | L21: 0 | O21: 0 | P21: 0 | Q21: 0 | V21: 0 | Z21: 0 | AA21: 0 | AB21: =AA21+H21 -> 0 | AD21: =C21 -> DTS_01 | BY21: =G21+J21 -> #VALUE! | CA21: DTS
A22: =IF(C22="","",A21+1) -> 8 | C22: DTS_02 | D22: Completed | E22: T&M | F22: Non-blockchain | G22: =B22&"_"&C22 -> _DTS_02 | L22: 0 | O22: 0 | P22: 0 | Q22: 0 | V22: 0 | Z22: 0 | AA22: 0 | AB22: =AA22+H22 -> 0 | AD22: =C22 -> DTS_02 | BY22: =G22+J22 -> #VALUE!
A23: =IF(C23="","",A22+1) -> 9 | C23: DTS_03 | D23: Completed | E23: T&M | F23: Non-blockchain | G23: =B23&"_"&C23 -> _DTS_03 | L23: 0 | O23: 0 | P23: 0 | Q23: 0 | V23: 0 | Z23: 0 | AA23: 0 | AB23: =AA23+H23 -> 0 | AD23: =C23 -> DTS_03
A24: 8 | B24: MOR | C24: MOR | D24: Completed | E24: T&M | F24: Non-blockchain | G24: =B24&"_"&C24 -> MOR_MOR | L24: 0 | O24: 0 | P24: 0 | Q24: 0 | V24: 0 | Z24: 0 | AA24: 0 | AB24: =AA24+H24 -> 0 | AD24: =C24 -> MOR | BY24: =G24+J24 -> #VALUE! | CA24: MOR
A25: =IF(C25="","",A24+1) -> 9 | B25: ICETEA | C25: ICETEA_Clevai onsite | D25: Completed | E25: T&M | F25: Non-blockchain | G25: =B25&"_"&C25 -> ICETEA_ICETEA_Clevai onsite | L25: 0 | O25: 0 | P25: 0 | Q25: 0 | V25: 0 | Z25: 0 | AA25: 0 | AB25: =AA25+H25 -> 0 | AD25: =C25 -> ICETEA_Clevai onsite | BY25: =G25+J25 -> #VALUE! | CA25: ICETEA_Clevai onsite
A26: =IF(C26="","",A25+1) -> 10 | C26: ICETEA_NCB onsite | D26: Completed | E26: T&M | F26: Non-blockchain | G26: =B26&"_"&C26 -> _ICETEA_NCB onsite | L26: 0 | O26: 0 | P26: 0 | Q26: 0 | V26: 0 | Z26: 0 | AA26: 0 | AB26: =AA26+H26 -> 0 | AD26: =C26 -> ICETEA_NCB onsite | BY26: =G26+J26 -> #VALUE! | CA26: ICETEA_NCB onsite
A27: 9 | B27: Sen Việt | C27: Sen Việt | D27: Completed | E27: Fixedprice | F27: Non-blockchain | G27: =B27&"_"&C27 -> Sen Việt_Sen Việt | L27: 0 | O27: 2535370 | P27: 2535370 | Q27: -2535370 | V27: 0 | Z27: 0 | AA27: 0 | AB27: =AA27+H27 -> 0 | AD27: =C27 -> Sen Việt | BY27: =G27+J27 -> #VALUE! | CA27: Sen Việt
A28: =IF(C28="","",A27+1) -> 10 | B28: Web3 | C28: Web3Research | D28: On-going | E28: T&M | F28: Blockchain | G28: =B28&"_"&C28 -> Web3_Web3Research | J28: 60406511 | L28: 60406511 | N28: 40090909 | P28: 40090909 | Q28: 20315602 | R28: 0.3363 | T28: 62798314 | V28: 62798314 | X28: 31043478 | Z28: 31043478 | AA28: 31754836 | AB28: =AA28+H28 -> 31754836 | AD28: =C28 -> Web3Research | BY28: =G28+J28 -> #VALUE! | CA28: Web3
A29: =IF(C29="","",A28+1) -> 11 | B29: Ái Việt | C29: Ái Việt | D29: Completed | E29: Fixedprice | F29: Non-blockchain | G29: =B29&"_"&C29 -> Ái Việt_Ái Việt | L29: 0 | O29: 0 | P29: 0 | Q29: 0 | V29: 0 | Z29: 0 | AA29: 0 | AB29: =AA29+H29 -> 0 | AD29: =C29 -> Ái Việt | BY29: =G29+J29 -> #VALUE! | CA29: Ái Việt
A30: 10 | B30: GTS | C30: GTS | D30: Completed | E30: T&M | F30: Non-blockchain | G30: =B30&"_"&C30 -> GTS_GTS | L30: 0 | O30: 0 | P30: 0 | Q30: 0 | V30: 0 | Z30: 0 | AA30: 0 | AB30: =AA30+H30 -> 0 | AD30: =C30 -> GTS | BY30: =G30+J30 -> #VALUE! | CA30: GTS
A31: =IF(C31="","",A30+1) -> 11 | B31: Thảo Nguyên | C31: Thảo Nguyên Shop_01 | D31: Completed | E31: Fixedprice | F31: Non-blockchain | G31: =B31&"_"&C31 -> Thảo Nguyên_Thảo Nguyên Shop_01 | L31: 0 | O31: 0 | P31: 0 | Q31: 0 | V31: 0 | Z31: 0 | AA31: 0 | AB31: =AA31+H31 -> 0 | AD31: =C31 -> Thảo Nguyên Shop_01 | BY31: =G31+J31 -> #VALUE! | CA31: Thảo Nguyên Shop_01
A32: =IF(C32="","",A31+1) -> 12 | C32: Thảo Nguyên Shop_02 | D32: Completed | E32: Fixedprice | F32: Non-blockchain | G32: =B32&"_"&C32 -> _Thảo Nguyên Shop_02 | L32: 0 | O32: 0 | P32: 0 | Q32: 0 | V32: 0 | Z32: 0 | AA32: 0 | AB32: =AA32+H32 -> 0 | AD32: =C32 -> Thảo Nguyên Shop_02 | BY32: =G32+J32 -> #VALUE! | CA32: Thảo Nguyên Shop_02
A33: 11 | C33: Thảo Nguyên Shop_03 | D33: Completed | E33: Fixedprice | F33: Non-blockchain | G33: =B33&"_"&C33 -> _Thảo Nguyên Shop_03 | L33: 0 | O33: 0 | P33: 0 | Q33: 0 | V33: 0 | Z33: 0 | AA33: 0 | AB33: =AA33+H33 -> 0 | AD33: =C33 -> Thảo Nguyên Shop_03 | BY33: =G33+J33 -> #VALUE!
A34: =IF(C34="","",A33+1) -> 12 | B34: MHS | C34: MHS | D34: Completed | E34: T&M | F34: Non-blockchain | G34: =B34&"_"&C34 -> MHS_MHS | L34: 0 | O34: 0 | P34: 0 | Q34: 0 | V34: 0 | Z34: 0 | AA34: 0 | AB34: =AA34+H34 -> 0 | AD34: =C34 -> MHS | BY34: =G34+J34 -> #VALUE! | CA34: MHS
A35: =IF(C35="","",A34+1) -> 13 | B35: SYSYEMEXE | C35: FLUZO | D35: Completed | E35: T&M | F35: Non-blockchain | G35: =B35&"_"&C35 -> SYSYEMEXE_FLUZO | L35: 0 | O35: 0 | P35: 0 | Q35: 0 | V35: 0 | Z35: 0 | AA35: 0 | AB35: =AA35+H35 -> 0 | AD35: =C35 -> FLUZO | BY35: =G35+J35 -> #VALUE!
A36: 12 | B36: ZINZA | C36: Zinza | D36: Completed | E36: T&M | F36: Blockchain | G36: =B36&"_"&C36 -> ZINZA_Zinza | L36: 0 | O36: 0 | P36: 0 | Q36: 0 | V36: 0 | Z36: 0 | AA36: 0 | AB36: =AA36+H36 -> 0 | AD36: =C36 -> Zinza | BY36: =G36+J36 -> #VALUE!
A37: =IF(C37="","",A36+1) -> 13 | B37: NDH | C37: Casoni | D37: Completed | E37: T&M | F37: Blockchain | G37: =B37&"_"&C37 -> NDH_Casoni | L37: 0 | O37: 0 | P37: 0 | Q37: 0 | V37: 0 | Z37: 0 | AA37: 0 | AB37: =AA37+H37 -> 0 | AD37: =C37 -> Casoni | BY37: =G37+J37 -> #VALUE! | CA37: 30240274
A38: =IF(C38="","",A37+1) -> 14 | B38: Hitek | C38: Hitek_Seegman | D38: Completed | E38: Fixedprice | F38: Non-blockchain | G38: =B38&"_"&C38 -> Hitek_Hitek_Seegman | L38: 0 | O38: 0 | P38: 0 | Q38: 0 | V38: 0 | Z38: 0 | AA38: 0 | AB38: =AA38+H38 -> 0 | AD38: =C38 -> Hitek_Seegman | BY38: =G38+J38 -> #VALUE!
A39: 13 | C39: Hitek_Allone2 | D39: Completed | E39: Fixedprice | F39: Non-blockchain | G39: =B39&"_"&C39 -> _Hitek_Allone2 | L39: 0 | O39: 0 | P39: 0 | Q39: 0 | V39: 0 | Z39: 0 | AA39: 0 | AB39: =AA39+H39 -> 0 | AD39: =C39 -> Hitek_Allone2 | BY39: =G39+J39 -> #VALUE!
A40: =IF(C40="","",A39+1) -> 14 | C40: Hitek_240 APIs | D40: Completed | E40: Fixedprice | F40: Non-blockchain | G40: =B40&"_"&C40 -> _Hitek_240 APIs | L40: 0 | O40: 0 | P40: 0 | Q40: 0 | V40: 0 | Z40: 0 | AA40: 0 | AB40: =AA40+H40 -> 0 | AD40: =C40 -> Hitek_240 APIs | BY40: =G40+J40 -> #VALUE!
A41: =IF(C41="","",A40+1) -> 15 | C41: Hitek_80 Pages Vuejs | D41: Completed | E41: Fixedprice | F41: Non-blockchain | G41: =B41&"_"&C41 -> _Hitek_80 Pages Vuejs | L41: 0 | O41: 0 | P41: 0 | Q41: 0 | V41: 0 | Z41: 0 | AA41: 0 | AB41: =AA41+H41 -> 0 | AC41: =Z41/0.58 -> 0 | AD41: =C41 -> Hitek_80 Pages Vuejs | BY41: =G41+J41 -> #VALUE!
A42: 14 | C42: Hitek_World Burger | D42: Completed | E42: Fixedprice | F42: Non-blockchain | G42: =B42&"_"&C42 -> _Hitek_World Burger | L42: 0 | O42: 0 | P42: 0 | Q42: 0 | V42: 0 | Z42: 0 | AA42: 0 | AB42: =AA42+H42 -> 0 | AD42: =C42 -> Hitek_World Burger | BY42: =G42+J42 -> #VALUE!
A43: =IF(C43="","",A42+1) -> 15 | C43: Hitek_Fillme | D43: Completed | E43: Fixedprice | F43: Non-blockchain | G43: =B43&"_"&C43 -> _Hitek_Fillme | L43: 0 | O43: 0 | P43: 0 | Q43: 0 | V43: 0 | Z43: 0 | AA43: 0 | AD43: =C43 -> Hitek_Fillme
A44: =IF(C44="","",A43+1) -> 16 | B44: Store 4H | C44: TRANHAN | D44: Completed | E44: Fixedprice | F44: Non-blockchain | G44: =B44&"_"&C44 -> Store 4H_TRANHAN | L44: 0 | O44: 0 | P44: 0 | Q44: 0 | V44: 0 | Z44: 0 | AA44: 0 | AB44: =AA44+H44 -> 0 | AD44: =C44 -> TRANHAN | BY44: =G44+J44 -> #VALUE!
A45: 15 | B45: Mikko | C45: Seitatech | D45: On-going | E45: T&M | F45: Non-blockchain | G45: =B45&"_"&C45 -> Mikko_Seitatech | J45: 72896565 | L45: 72896565 | N45: 47727273 | P45: 47727273 | Q45: 25169292 | R45: 0.3453 | T45: 77163000 | V45: 77163000 | X45: 36956522 | Z45: 36956522 | AA45: 40206478 | AB45: =AA45+H45 -> 40206478 | AD45: =C45 -> Seitatech | BY45: =G45+J45 -> #VALUE!
A46: =IF(C46="","",A45+1) -> 16 | B46: mPOS | C46: mPOS | D46: On-going | F46: Non-blockchain | G46: =B46&"_"&C46 -> mPOS_mPOS | L46: 0 | O46: 0 | P46: 0 | Q46: 0 | V46: 0 | Z46: 0 | AA46: 0 | AB46: =AA46+H46 -> 0 | AD46: =C46 -> mPOS | BY46: =G46+J46 -> #VALUE!
A47: =IF(C47="","",A46+1) -> 17 | B47: ETH | C47: R&D | D47: On-going | F47: Blockchain | G47: =B47&"_"&C47 -> ETH_R&D | L47: 0 | O47: 0 | P47: 0 | Q47: 0 | V47: 0 | Z47: 0 | AA47: 0 | AB47: =AA47+H47 -> 0 | AD47: =C47 -> R&D | BY47: =G47+J47 -> #VALUE!
A48: 16 | B48: Femi | C48: MRA | D48: Completed | E48: Fixedprice | F48: Non-blockchain | G48: =B48&"_"&C48 -> Femi_MRA | L48: 0 | O48: 0 | P48: 0 | Q48: 0 | V48: 0 | Z48: 0 | AA48: 0 | AB48: =AA48+H48 -> 0 | AD48: =C48 -> MRA | BY48: =G48+J48 -> #VALUE!
A49: =IF(C49="","",A48+1) -> 17 | B49: Oliver | C49: Sundance website - rebuild | D49: Completed | E49: Fixedprice | F49: Non-blockchain | G49: =B49&"_"&C49 -> Oliver_Sundance website - rebuild | L49: 0 | O49: 0 | P49: 0 | Q49: 0 | V49: 0 | Z49: 0 | AA49: 0 | AB49: =AA49+H49 -> 0 | AD49: =C49 -> Sundance website - rebuild | BY49: =G49+J49 -> #VALUE!
A50: =IF(C50="","",A49+1) -> 18 | C50: DevOps consulting | D50: Completed | E50: T&M | F50: Non-blockchain | G50: =B50&"_"&C50 -> _DevOps consulting | J50: 10454000 | L50: 10454000 | N50: 1949900 | P50: 1949900 | Q50: 8504100 | R50: 0.8135 | V50: 0 | Z50: 0 | AA50: 0 | AB50: =AA50+H50 -> 0 | AD50: =C50 -> DevOps consulting | BY50: =G50+J50 -> #VALUE!
A51: 17 | B51: Collab | C51: W3L_Purr.fund | D51: On-going | F51: Blockchain | G51: =B51&"_"&C51 -> Collab_W3L_Purr.fund | L51: 0 | O51: 0 | P51: 0 | Q51: 0 | V51: 0 | Z51: 0 | AA51: 0 | AB51: =AA51+H51 -> 0 | AD51: =C51 -> W3L_Purr.fund | BY51: =G51+J51 -> #VALUE!
A52: =IF(C52="","",A51+1) -> 18 | C52: Seagate | D52: On-going | F52: Blockchain | G52: =B52&"_"&C52 -> _Seagate | L52: 0 | O52: 0 | P52: 0 | Q52: 0 | V52: 0 | Z52: 0 | AA52: 0 | AB52: =AA52+H52 -> 0 | AD52: =C52 -> Seagate | BY52: =G52+J52 -> #VALUE!
A53: =IF(C53="","",A52+1) -> 19 | B53: Evocean | C53: Moonkit | D53: On-going | F53: Blockchain | G53: =B53&"_"&C53 -> Evocean_Moonkit | L53: 0 | O53: 0 | P53: 0 | Q53: 0 | V53: 0 | Z53: 0 | AA53: 0 | AB53: =AA53+H53 -> 0 | AD53: =C53 -> Moonkit | BY53: =G53+J53 -> #VALUE!
A54: 18 | B54: Tonka EZ | C54: Tonka_Restaking with Capi | D54: Completed | E54: Fixedprice | F54: Blockchain | G54: =B54&"_"&C54 -> Tonka EZ _Tonka_Restaking with Capi | L54: 0 | O54: 0 | P54: 0 | Q54: 0 | V54: 0 | Z54: 0 | AA54: 0 | AB54: =AA54+H54 -> 0 | AD54: =C54 -> Tonka_Restaking with Capi | BY54: =G54+J54 -> #VALUE!
A55: =IF(C55="","",A54+1) -> 19 | B55: Golive | C55: Golive_Golang | D55: Completed | E55: T&M | F55: Non-blockchain | G55: =B55&"_"&C55 -> Golive_Golive_Golang | L55: 0 | O55: 0 | P55: 0 | Q55: 0 | V55: 0 | Z55: 0 | AA55: 0 | AB55: =AA55+H55 -> 0 | AD55: =C55 -> Golive_Golang | BY55: =G55+J55 -> #VALUE!
A56: =IF(C56="","",A55+1) -> 20 | B56: c/o Roy | C56: Saltmines | D56: Completed | E56: T&M | F56: Blockchain | G56: =B56&"_"&C56 -> c/o Roy_Saltmines | L56: 0 | O56: 0 | P56: 0 | Q56: 0 | V56: 0 | Z56: 0 | AA56: 0 | AB56: =AA56+H56 -> 0 | AD56: =C56 -> Saltmines | BY56: =G56+J56 -> #VALUE!
A57: 19 | B57: LunaShop | C57: Lunashop | D57: Completed | E57: Fixedprice | F57: Non-blockchain | G57: =B57&"_"&C57 -> LunaShop_Lunashop | L57: 0 | O57: 0 | P57: 0 | Q57: 0 | V57: 0 | Z57: 0 | AA57: 0 | AB57: =AA57+H57 -> 0 | AD57: =C57 -> Lunashop | BY57: =G57+J57 -> #VALUE! | BZ57: =F57/E57 -> #VALUE!
A58: =IF(C58="","",A57+1) -> 20 | B58: Trinity | C58: Fomoney | D58: On-going | E58: Fixedprice | F58: Blockchain | G58: =B58&"_"&C58 -> Trinity_Fomoney | L58: 0 | O58: 0 | P58: 0 | Q58: 0 | V58: 0 | Z58: 0 | AA58: 0 | AB58: =AA58+H58 -> 0 | AD58: =C58 -> Fomoney | BY58: =G58+J58 -> #VALUE!
A59: =IF(C59="","",A58+1) -> 21 | B59: QSOFT | C59: Transparently | D59: On-going | E59: T&M | F59: Non-blockchain | G59: =B59&"_"&C59 -> QSOFT_Transparently | J59: 138325000 | L59: 138325000 | N59: 77142500 | P59: 77142500 | Q59: 61182500 | R59: 0.4423 | T59: 102971947 | V59: 102971947 | X59: 57018370 | Z59: 57018370 | AA59: 45953577 | AB59: =AA59+H59 -> 45953577 | AD59: =C59 -> Transparently | BY59: =G59+J59 -> #VALUE!
A60: 20 | B60: VCCI | C60: Alumni | D60: On-going | F60: Non-blockchain | G60: =B60&"_"&C60 -> VCCI_Alumni | L60: 0 | O60: 0 | P60: 0 | Q60: 0 | V60: 0 | Z60: 0 | AA60: 0 | AB60: =AA60+H60 -> 0 | AD60: =C60 -> Alumni | BY60: =G60+J60 -> #VALUE!
A61: =IF(C61="","",A60+1) -> 21 | B61: Kostas | C61: Kostas-off shore | D61: Completed | E61: T&M | F61: Blockchain | G61: =B61&"_"&C61 -> Kostas_Kostas-off shore | L61: 0 | O61: 0 | P61: 0 | Q61: 0 | V61: 0 | Z61: 0 | AA61: 0 | AB61: =AA61+H61 -> 0 | AD61: =C61 -> Kostas-off shore | BY61: =G61+J61 -> #VALUE!
A62: =IF(C62="","",A61+1) -> 22 | B62: Tonka | C62: AYB Landing page | D62: Completed | E62: Fixedprice | F62: Blockchain | G62: =B62&"_"&C62 -> Tonka_AYB Landing page | L62: 0 | O62: 0 | P62: 0 | Q62: 0 | V62: 0 | Z62: 0 | AA62: 0 | AB62: =AA62+H62 -> 0 | AD62: =C62 -> AYB Landing page | BY62: =G62+J62 -> #VALUE!
A63: 21 | C63: AI OCR | D63: On-going | F63: Non-blockchain | G63: =B63&"_"&C63 -> _AI OCR | L63: 0 | O63: 0 | P63: 0 | Q63: 0 | V63: 0 | Z63: 0 | AA63: 0 | AB63: =AA63+H63 -> 0 | AD63: =C63 -> AI OCR | BY63: =G63+J63 -> #VALUE!
A64: =IF(C64="","",A63+1) -> 22 | B64: Inhouse | C64: Warmfeet | D64: On-going | F64: Non-blockchain | G64: =B64&"_"&C64 -> Inhouse_Warmfeet | L64: 0 | O64: 0 | P64: 0 | Q64: 0 | V64: 0 | Z64: 0 | AA64: 0 | AB64: =AA64+H64 -> 0 | AD64: =C64 -> Warmfeet | BY64: =G64+J64 -> #VALUE!
A65: =IF(C65="","",A64+1) -> 23 | B65: Anis Carmats | C65: Shopify | D65: Completed | E65: Fixedprice | F65: Non-blockchain | G65: =B65&"_"&C65 -> Anis Carmats_Shopify | L65: 0 | O65: 0 | P65: 0 | Q65: 0 | V65: 0 | Z65: 0 | AA65: 0 | AB65: =AA65+H65 -> 0 | AD65: =C65 -> Shopify | BY65: =G65+J65 -> #VALUE!
A66: 22 | B66: Prediction on Sol | C66: Naoer (MRC20) | D66: On-going | E66: Fixedprice | F66: Blockchain | G66: =B66&"_"&C66 -> Prediction on Sol_Naoer (MRC20) | L66: 0 | O66: 0 | P66: 0 | Q66: 0 | V66: 0 | Z66: 0 | AA66: 0 | AB66: =AA66+H66 -> 0 | AD66: =C66 -> Naoer (MRC20) | BY66: =G66+J66 -> #VALUE!
A67: =IF(C67="","",A66+1) -> 23 | B67: Lee | C67: InuTap Bot | D67: Completed | E67: Fixedprice | F67: Blockchain | G67: =B67&"_"&C67 -> Lee_ InuTap Bot | L67: 0 | O67: 0 | P67: 0 | Q67: 0 | V67: 0 | Z67: 0 | AA67: 0 | AB67: =AA67+H67 -> 0 | AD67: =C67 -> InuTap Bot | BY67: =G67+J67 -> #VALUE!
A68: =IF(C68="","",A67+1) -> 24 | B68: MOHA | C68: MOHA_Watashino Application | D68: Completed | E68: T&M | F68: Non-blockchain | G68: =B68&"_"&C68 -> MOHA_MOHA_Watashino Application | L68: 0 | O68: 0 | P68: 0 | Q68: 0 | V68: 0 | Z68: 0 | AA68: 0 | AB68: =AA68+H68 -> 0 | AD68: =C68 -> MOHA_Watashino Application | BY68: =G68+J68 -> #VALUE!
A69: 23 | B69: Golive | C69: Golive_PHP | D69: Completed | E69: Fixedprice | F69: Non-blockchain | G69: =B69&"_"&C69 -> Golive_Golive_PHP | L69: 0 | O69: 0 | P69: 0 | Q69: 0 | V69: 0 | Z69: 0 | AA69: 0 | AB69: =AA69+H69 -> 0 | AD69: =C69 -> Golive_PHP | BY69: =G69+J69 -> #VALUE!
A70: =IF(C70="","",A69+1) -> 24 | B70: Inhouse | C70: Internal sourcing | D70: On-going | F70: Blockchain | G70: =B70&"_"&C70 -> Inhouse_Internal sourcing | L70: 0 | O70: 0 | P70: 0 | Q70: 0 | V70: 0 | Z70: 0 | AA70: 0 | AB70: =AA70+H70 -> 0 | AD70: =C70 -> Internal sourcing | BY70: =G70+J70 -> #VALUE!
A71: =IF(C71="","",A70+1) -> 25 | B71: C0ins | C71: Whatexchange | D71: Completed | E71: Fixedprice | F71: Blockchain | G71: =B71&"_"&C71 -> C0ins_Whatexchange | L71: 0 | O71: 0 | P71: 0 | Q71: 0 | V71: 0 | Z71: 0 | AA71: 0 | AB71: =AA71+H71 -> 0 | AD71: =C71 -> Whatexchange | BY71: =G71+J71 -> #VALUE!
A72: 24 | C72: Racer BSX | D72: Completed | E72: Fixedprice | F72: Blockchain | G72: =B72&"_"&C72 -> _Racer BSX | L72: 0 | O72: 0 | P72: 0 | Q72: 0 | V72: 0 | Z72: 0 | AA72: 0 | AB72: =AA72+H72 -> 0 | AD72: =C72 -> Racer BSX | BY72: =G72+J72 -> #VALUE!
A73: =IF(C73="","",A72+1) -> 25 | B73: HOLA | C73: Hola_MB | D73: Completed | E73: T&M | F73: Blockchain | G73: =B73&"_"&C73 -> HOLA_Hola_MB | L73: 0 | O73: 0 | P73: 0 | Q73: 0 | V73: 0 | Z73: 0 | AA73: 0 | AB73: =AA73+H73 -> 0 | AD73: =C73 -> Hola_MB | BY73: =G73+J73 -> #VALUE!
A74: =IF(C74="","",A73+1) -> 26 | B74: Hùng | C74: Tabswap/ Unicorn City | D74: On-going | E74: Fixedprice | F74: Blockchain | G74: =B74&"_"&C74 -> Hùng_Tabswap/ Unicorn City | L74: 0 | O74: 0 | P74: 0 | Q74: 0 | V74: 0 | Z74: 0 | AA74: 0 | AB74: =AA74+H74 -> 0 | AD74: =C74 -> Tabswap/ Unicorn City | BY74: =G74+J74 -> #VALUE!
A75: 25 | B75: Anicho | C75: Sniper tool | D75: Completed | E75: Fixedprice | F75: Blockchain | G75: =B75&"_"&C75 -> Anicho_Sniper tool | L75: 0 | O75: 0 | P75: 0 | Q75: 0 | V75: 0 | Z75: 0 | AA75: 0 | AB75: =AA75+H75 -> 0 | AD75: =C75 -> Sniper tool | BY75: =G75+J75 -> #VALUE!
A76: =IF(C76="","",A75+1) -> 26 | B76: Hitek | C76: Hitek_Buptle/Python | D76: On-going | E76: T&M | F76: Non-blockchain | G76: =B76&"_"&C76 -> Hitek_Hitek_Buptle/Python | J76: 71304000 | L76: 71304000 | N76: 45956522 | P76: 45956522 | Q76: 25347478 | R76: 0.3555 | V76: 0 | Z76: 0 | AA76: 0 | AB76: =AA76+H76 -> 0 | AD76: =C76 -> Hitek_Buptle/Python | BY76: =G76+J76 -> #VALUE!
A77: =IF(C77="","",A76+1) -> 27 | B77: QSOFT | C77: Prudential | D77: On-going | E77: T&M | F77: Non-blockchain | G77: =B77&"_"&C77 -> QSOFT_Prudential | J77: 67905000 | L77: 67905000 | N77: 49310000 | P77: 49310000 | Q77: 18595000 | R77: 0.2738 | T77: 50549865 | V77: 50549865 | X77: 36446522 | Z77: 36446522 | AA77: 14103343 | AB77: =AA77+H77 -> 14103343 | AD77: =C77 -> Prudential | BY77: =G77+J77 -> #VALUE!
A78: 26 | B78: QSOFT | C78: Pinnacle | D78: On-going | E78: T&M | F78: Non-blockchain | G78: =B78&"_"&C78 -> QSOFT_Pinnacle | J78: 379650693 | L78: 379650693 | N78: 226831909 | P78: 226831909 | Q78: 152818784 | R78: 0.4025 | T78: 303299140 | V78: 303299140 | X78: 198257695 | Z78: 198257695 | AA78: 105041445 | AB78: =AA78+H78 -> 105041445 | AD78: =C78 -> Pinnacle | BY78: =G78+J78 -> #VALUE!
A79: =IF(C79="","",A78+1) -> 27 | B79: GTS | C79: GTS_Python | D79: Completed | E79: T&M | F79: Non-blockchain | G79: =B79&"_"&C79 -> GTS_GTS_Python | L79: 0 | O79: 0 | P79: 0 | Q79: 0 | V79: 0 | Z79: 0 | AA79: 0 | AB79: =AA79+H79 -> 0 | AD79: =C79 -> GTS_Python
A80: =IF(C80="","",A79+1) -> 28 | B80: Inhouse | C80: Training | D80: On-going | F80: Non-blockchain | G80: =B80&"_"&C80 -> Inhouse_Training | L80: 0 | O80: 0 | P80: 0 | Q80: 0 | V80: 0 | Z80: 0 | AA80: 0 | AB80: =AA80+H80 -> 0 | AD80: =C80 -> Training
A81: 27 | B81: ACCOMY | C81: Hotel D-Hub | D81: Completed | E81: Fixedprice | F81: Blockchain | G81: =B81&"_"&C81 -> ACCOMY_Hotel D-Hub | L81: 0 | O81: 0 | P81: 0 | Q81: 0 | U81: 104677892 | V81: 104677892 | W81: 0 | Z81: 0 | AA81: 104677892 | AB81: =AA81+H81 -> 104677892 | AD81: =C81 -> Hotel D-Hub
A82: =IF(C82="","",A81+1) -> 28 | B82: Femi | C82: Certus | D82: Completed | E82: Fixedprice | F82: Non-blockchain | G82: =B82&"_"&C82 -> Femi_Certus | L82: 0 | O82: 110008763 | P82: 110008763 | Q82: -110008763 | V82: 0 | Z82: 0 | AA82: 0 | AB82: =AA82+H82 -> 0 | AD82: =C82 -> Certus
A83: =IF(C83="","",A82+1) -> 29 | B83: Anis Carmats | C83: Cartints | D83: Completed | E83: Fixedprice | F83: Blockchain | G83: =B83&"_"&C83 -> Anis Carmats_Cartints | L83: 0 | O83: 0 | P83: 0 | Q83: 0 | V83: 0 | Z83: 0 | AA83: 0 | AB83: =AA83+H83 -> 0 | AD83: =C83 -> Cartints
A84: 28 | B84: Max | C84: Tonuki | D84: Completed | E84: Fixedprice | F84: Blockchain | G84: =B84&"_"&C84 -> Max_Tonuki | L84: 0 | O84: 0 | P84: 0 | Q84: 0 | V84: 0 | Z84: 0 | AA84: 0 | AB84: =AA84+H84 -> 0 | AD84: =C84 -> Tonuki
A85: =IF(C85="","",A84+1) -> 29 | B85: Honeypot | C85: Honeypot | D85: Completed | E85: Fixedprice | F85: Blockchain | G85: =B85&"_"&C85 -> Honeypot_Honeypot | L85: 0 | O85: 0 | P85: 0 | Q85: 0 | V85: 0 | Z85: 0 | AA85: 0 | AB85: =AA85+H85 -> 0 | AD85: =C85 -> Honeypot
A86: =IF(C86="","",A85+1) -> 30 | B86: Erik | C86: Taiboku-volume bot | D86: Completed | E86: Fixedprice | F86: Blockchain | G86: =B86&"_"&C86 -> Erik_Taiboku-volume bot | L86: 0 | O86: 0 | P86: 0 | Q86: 0 | V86: 0 | Z86: 0 | AA86: 0 | AB86: =AA86+H86 -> 0 | AD86: =C86 -> Taiboku-volume bot
A87: 29 | B87: Erik | C87: EVM Volume Botm | D87: Completed | E87: Fixedprice | F87: Blockchain | G87: =B87&"_"&C87 -> Erik_EVM Volume Botm | L87: 0 | O87: 0 | P87: 0 | Q87: 0 | V87: 0 | Z87: 0 | AA87: 0 | AB87: =AA87+H87 -> 0 | AD87: =C87 -> EVM Volume Botm
A88: =IF(C88="","",A87+1) -> 30 | B88: Kelly Vui | C88: Kelly Website | D88: On-going | E88: Fixedprice | F88: Non-blockchain | G88: =B88&"_"&C88 -> Kelly Vui_Kelly Website | L88: 0 | O88: 0 | P88: 0 | Q88: 0 | V88: 0 | Z88: 0 | AA88: 0 | AB88: =AA88+H88 -> 0 | AD88: =C88 -> Kelly Website
A89: =IF(C89="","",A88+1) -> 31 | B89: Inhouse | C89: Self-learning | D89: On-going | F89: Non-blockchain | G89: =B89&"_"&C89 -> Inhouse_Self-learning | L89: 0 | O89: 30326336 | P89: 30326336 | Q89: -30326336 | V89: 0 | Z89: 0 | AA89: 0 | AB89: =AA89+H89 -> 0 | AD89: =C89 -> Self-learning
A90: 30 | B90: Inhouse | C90: King Meme | D90: On-going | E90: Fixedprice | F90: Blockchain | G90: =B90&"_"&C90 -> Inhouse_King Meme | L90: 0 | O90: 54197073 | P90: 54197073 | Q90: -54197073 | V90: 0 | Z90: 0 | AA90: 0 | AB90: =AA90+H90 -> 0 | AD90: =C90 -> King Meme
A91: =IF(C91="","",A90+1) -> 31 | B91: Inhouse | C91: Xipple Fi | D91: On-going | E91: Fixedprice | F91: Blockchain | G91: =B91&"_"&C91 -> Inhouse_Xipple Fi | L91: 0 | O91: 0 | P91: 0 | Q91: 0 | V91: 0 | Z91: 0 | AA91: 0 | AB91: =AA91+H91 -> 0 | AD91: =C91 -> Xipple Fi
A92: =IF(C92="","",A91+1) -> 32 | B92: cRoy | C92: Memest | D92: On-going | E92: Fixedprice | F92: Blockchain | G92: =B92&"_"&C92 -> cRoy_Memest | L92: 0 | O92: 0 | P92: 0 | Q92: 0 | U92: 97439265 | V92: 97439265 | Z92: 0 | AA92: 97439265 | AB92: =AA92+H92 -> 97439265 | AD92: =C92 -> Memest
A93: 31 | B93: GTS | C93: GTS_Onepay | D93: On-going | E93: T&M | F93: Non-blockchain | G93: =B93&"_"&C93 -> GTS_GTS_Onepay | I93: 78609000 | L93: 78609000 | M93: 61356091 | P93: 61356091 | Q93: 17252909 | R93: 0.2195 | S93: 58417000 | V93: 58417000 | W93: 55118512 | Z93: 55118512 | AA93: 3298488 | AB93: =AA93+H93 -> 3298488 | AD93: =C93 -> GTS_Onepay
A94: =IF(C94="","",A93+1) -> 32 | B94: Max | C94: Tonuki_2dev | D94: Completed | E94: T&M | F94: Blockchain | G94: =B94&"_"&C94 -> Max_Tonuki_2dev | K94: 39786130 | L94: 39786130 | M94: 36177533 | P94: 36177533 | Q94: 3608597 | R94: 0.0907 | S94: 39786130 | V94: 39786130 | Z94: 0 | AA94: 39786130 | AB94: =AA94+H94 -> 39786130 | AD94: =C94 -> Tonuki_2dev
A95: =IF(C95="","",A94+1) -> 33 | B95: Erik | C95: Taiboku - Limit Orders Bot [EVM] | D95: Completed | E95: Fixedprice | F95: Blockchain | G95: =B95&"_"&C95 -> Erik_Taiboku - Limit Orders Bot [EVM] | L95: 0 | O95: 0 | P95: 0 | Q95: 0 | V95: 0 | Z95: 0 | AA95: 0 | AB95: =AA95+H95 -> 0 | AD95: =C95 -> Taiboku - Limit Orders Bot [EVM]
A96: 32 | B96: Erik | C96: Taiboku - Volume Bot [SOL] | D96: Completed | E96: Fixedprice | F96: Blockchain | G96: =B96&"_"&C96 -> Erik_Taiboku - Volume Bot [SOL] | L96: 0 | O96: 0 | P96: 0 | Q96: 0 | V96: 0 | Z96: 0 | AA96: 0 | AB96: =AA96+H96 -> 0 | AD96: =C96 -> Taiboku - Volume Bot [SOL]
A97: =IF(C97="","",A96+1) -> 33 | B97: Erik | C97: Taiboku - Server & Dashboard For Interacting with Volume Bots | D97: Completed | E97: Fixedprice | F97: Blockchain | G97: =B97&"_"&C97 -> Erik_Taiboku - Server & Dashboard For Interacting with Volume Bots | L97: 0 | O97: 0 | P97: 0 | Q97: 0 | V97: 0 | Z97: 0 | AA97: 0 | AB97: =AA97+H97 -> 0 | AD97: =C97 -> Taiboku - Server & Dashboard For Interacting with Volume Bots
A98: =IF(C98="","",A97+1) -> 34 | B98: cRoy | C98: Saltmines - Memest Private Round | D98: Completed | E98: Fixedprice | F98: Blockchain | G98: =B98&"_"&C98 -> cRoy_Saltmines - Memest Private Round | L98: 0 | O98: 0 | P98: 0 | Q98: 0 | V98: 0 | Z98: 0 | AA98: 0 | AB98: =AA98+H98 -> 0 | AD98: =C98 -> Saltmines - Memest Private Round
A99: 33 | B99: Smart-solutions | C99: Pramis onsite | D99: Completed | E99: T&M | F99: Non-blockchain | G99: =B99&"_"&C99 -> Smart-solutions_Pramis onsite | I99: 19702000 | L99: 19702000 | M99: 11467673 | P99: 11467673 | Q99: 8234327 | R99: 0.4179 | V99: 0 | Z99: 0 | AA99: 0 | AB99: =AA99+H99 -> 0 | AD99: =C99 -> Pramis onsite
A100: =IF(C100="","",A99+1) -> 34 | B100: Honeypot | C100: Honeypot Fjord/Update Filter | D100: Completed | E100: Fixedprice | F100: Blockchain | G100: =B100&"_"&C100 -> Honeypot_Honeypot Fjord/Update Filter | I100: 12634000 | L100: 12634000 | M100: 0 | P100: 0 | Q100: 12634000 | R100: 1 | V100: 0 | Z100: 0 | AA100: 0 | AB100: =AA100+H100 -> 0 | AD100: =C100 -> Honeypot Fjord/Update Filter
...
